{"agree":"[əˈɡriː]","augment":"[ɔːɡˈment]","alignment":"[əˈlaɪnmənt]","aid":"[eɪd]","assembler":"[əˈsemblə(r)]","assemble":"[əˈsembl]","alphabet":"[ˈælfəbet]","assortment":"[əˈsɔːtmənt]","anticipate":"[ænˈtɪsɪpeɪt]","acknowledgment":"[ək'nɒlɪdʒmənt]","avail":"[əˈveɪl]","advanced":"[ədˈvɑːnst]","american":"[əˈmerɪkən]","average":"[ˈævərɪdʒ]","attached":"[əˈtætʃt]","announce":"[əˈnaʊns]","absence":"[ˈæbsəns]","accuracy":"[ˈækjərəsi]","ampersand":"[ˈæmpəsænd]","administrator":"[ədˈmɪnɪstreɪtə(r)]","autoindex":"[,ɔ:təu'indeks]","accidentally":"[ˌæksɪˈdentəli]","additionally":"[əˈdɪʃənəli]","away":"[əˈweɪ]","ansi":"['ænsi]","ally":"[ˈælaɪ]","alpha":"[ˈælfə]","against":"[əˈɡenst; əˈɡeɪnst]","activity":"[ækˈtɪvəti]","advice":"[ədˈvaɪs]","ability":"[əˈbɪləti]","accelerator":"[əkˈseləreɪtə(r)]","angle":"[ˈæŋɡl]","appendix":"[əˈpendɪks]","apple":"[ˈæpl]","alphabetically":"[ˌælfəˈbetɪkli]","attention":"[əˈtenʃn]","abort":"[əˈbɔːt]","answer":"[ˈɑːnsə(r)]","allowed":"","affected":"[əˈfektɪd]","anywhere":"[ˈeniweə(r)]","aligned":"[ə'laɪn]","auto":"[ˈɔːtəʊ]","addressing":"[ə'drəsɪŋ]","analyst":"[ˈænəlɪst]","anytime":"['enɪtaɪm]","achieve":"[əˈtʃiːv]","applied":"[əˈplaɪd]","alternately":"[ɔːlˈtɜːnətli]","assumed":"[əˈsjuːmd]","asterisk":"[ˈæstərɪsk]","accept":"[əkˈsept]","along":"[əˈlɒŋ]","although":"[ɔːlˈðəʊ]","assembly":"[əˈsembli]","additive":"[ˈædətɪv]","according":"[ə'kɔːdɪŋ]","ask":"[ɑːsk]","able":"[ˈeɪbl]","activate":"[ˈæktɪveɪt]","aboveboard":"[ə,bʌv'bɔːd]","abbreviation":"[əˌbriːviˈeɪʃn]","above":"[əˈbʌv]","assistance":"[əˈsɪstəns]","across":"[əˈkrɒs]","always":"[ˈɔːlweɪz]","again":"[əˈɡen; əˈɡeɪn]","ascii":"[ˈæski]","abbreviate":"[əˈbriːvieɪt]","arrow":"[ˈærəʊ]","allow":"[əˈlaʊ]","about":"[əˈbaʊt]","after":"[ˈɑːftə(r)]","another":"[əˈnʌðə(r)]","appear":"[əˈpɪə(r)]","also":"[ˈɔːlsəʊ]","all":"[ɔːl]","aware":"[əˈweə(r)]","awakened":"","awaken":"[əˈweɪkən]","avoid":"[əˈvɔɪd]","available":"[əˈveɪləbl]","automatically":"[ˌɔːtəˈmætɪkli]","automatic":"[ˌɔːtəˈmætɪk]","autoboxing":"","authorized":"['ɔːθəraɪzd]","authorize":"[ˈɔːθəraɪz]","author":"[ˈɔːθə(r)]","authentication":"[ɔːˌθentɪˈkeɪʃn]","auditing":"['ɔːdɪtɪŋ 　]","attribute":"[əˈtrɪbjuːt]","attempt to…":"","attempt":"[əˈtempt]","attachment":"[əˈtætʃmənt]","attach":"[əˈtætʃ]","atomically":"","atomic":"[əˈtɒmɪk]","athlete":"[ˈæθliːt]","at the same time":"","at once":"","at most":"","at least":"","as large as":"","asynchronous":"[eɪˈsɪŋkrənəs]","assure":"[əˈʃʊə(r); əˈʃɔː(r)]","assume":"[əˈsjuːm]","association":"[əˌsəʊsiˈeɪʃn; əˌsəʊʃiˈeɪʃn]","associated with…":"","associated":"[əˈsəʊsieɪtɪd; əˈsəʊʃieɪtɪd]","associate":"[əˈsəʊsieɪt; əˈsəʊʃieɪt]","assist":"[əˈsɪst]","assignment":"[əˈsaɪnmənt]","assign…to…":"","assigned":"[əˈsaɪnd]","assign":"[əˈsaɪn]","assertion":"[əˈsɜːʃn]","aspect":"[ˈæspekt]","as well as":"","as necessary":"","as much as":"","as for…":"","ascending":"[ə'sendɪŋ]","ascend":"[əˈsend]","as with…":"","as to…":"","as soon as…":"","as of…":"","as long as...":"","as if…":"","as follows":"","as by…":"","as a result of…":"","array":"[əˈreɪ]","arrange":"[əˈreɪndʒ]","around":"[əˈraʊnd]","arithmetic":"[əˈrɪθmətɪk]","arise":"[əˈraɪz]","argument":"[ˈɑːɡjumənt]","area":"[ˈeəriə]","archive":"[ˈɑːrkaɪv]","architecture":"[ˈɑːkɪtektʃə(r)]","arbitrary":"[ˈɑːbɪtrəri; ˈɑːbɪtri]","approximation":"[əˌprɒksɪˈmeɪʃn]","approximately":"[əˈprɒksɪmətli]","approximate":"[ə'prɒksɪmət]","appropriately":"[əˈprəʊpriətli]","appropriate":"[əˈprəʊpriət]","apply to…":"","apply":"[əˈplaɪ]","application-specific":"","application":"[ˌæplɪˈkeɪʃn]","applicable":"[əˈplɪkəbl; ˈæplɪkəbl]","append":"[əˈpend]","appearance":"[əˈpɪərəns]","ant":"[ænt]","anonymous":"[əˈnɒnɪməs]","annotation":"[ˌænəˈteɪʃn]","annotated":"[ˈænəteɪtɪd]","animate":"[ˈænɪmeɪt]","angel":"[ˈeɪndʒl]","anchor":"[ˈæŋkə(r)]","ancestor":"[ˈænsestə(r)]","analysis":"[əˈnæləsɪs]","amount":"[əˈmaʊnt]","amortized":"","amongst":"[ə'mʌŋst]","among":"[əˈmʌŋ]","ambiguous":"[æmˈbɪɡjuəs]","ambiguity":"[ˌæmbɪˈɡjuːəti]","alternative":"[ɔːlˈtɜːnətɪv]","alternate":"[ɔːlˈtɜːnət]","alter":"[ˈɔːltə(r)]","already":"[ɔːlˈredi]","alphanumeric":"[ˌælfənjuːˈmerɪk]","alphabetical":"[ˌælfəˈbetɪkl]","along with…":"","alone":"[əˈləʊn]","allowable":"[əˈlaʊəbl]","alow":"[ə'ləʊ]","allocation":"[ˌæləˈkeɪʃn]","allocate":"[ˈæləkeɪt]","algorithm":"[ˈælɡərɪðəm]","align":"[əˈlaɪn]","alias":"[ˈeɪliəs]","alert":"[əˈlɜːt]","ahead":"[əˈhed]","affect":"[əˈfekt]","advise":"[ədˈvaɪz]","advance..past..":"","advance":"[ədˈvɑːns]","adjust":"[əˈdʒʌst]","adjacent":"[əˈdʒeɪsnt]","address":"[əˈdres]","additional":"[əˈdɪʃənl]","addition":"[əˈdɪʃn]","adequate":"[ˈædɪkwət]","add":"[æd]","adapter":"[ə'dæptə]","adaptation":"[ˌædæpˈteɪʃn]","across…":"[əˈkrɒs]","actually":"[ˈæktʃuəli]","actual":"[ˈæktʃuəl]","actively":"[ˈæktɪvli]","active":"[ˈæktɪv]","activation":"[ˌæktɪˈveɪʃn]","action":"[ˈækʃn]","act as…":"","accurate":"[ˈækjərət]","accumulate":"[əˈkjuːmjəleɪt]","accountable":"[əˈkaʊntəbl]","account":"[əˈkaʊnt]","accordion":"[əˈkɔːdiən]","accomplish":"[əˈkʌmplɪʃ]","accompany":"[əˈkʌmpəni]","accommodate":"[əˈkɒmədeɪt]","accidental":"[ˌæksɪˈdentl]","accessor":"['əksesər]","accessible":"[əkˈsesəbl]","accessed":"","access":"[ˈækses]","abstraction":"[æbˈstrækʃn]","abstract":"[ˈæbstrækt]","basis":"[ˈbeɪsɪs]","big":"[bɪɡ]","book":"[bʊk]","blast":"[blɑːst]","becoming":"[bɪˈkʌmɪŋ]","british":"[ˈbrɪtɪʃ]","board":"[bɔːd]","bus":"[bʌs]","bracketed":"['brækətɪd]","building":"[ˈbɪldɪŋ]","busy":"[ˈbɪzi]","bell":"[bel]","bad":"[bæd]","brown":"[braʊn]","boot":"[buːt]","buy":"[baɪ]","black":"[blæk]","bit":"[bɪt]","blue":"[bluː]","beep":"[biːp]","become":"[bɪˈkʌm]","blinking":"[ˈblɪŋkɪŋ]","bring":"[brɪŋ]","branch":"[brɑːntʃ]","bios":"['baɪɒs]","below":"[bɪˈləʊ]","bracket":"[ˈbrækɪt]","both":"[bəʊθ]","begin":"[bɪˈɡɪn]","but":"[bət; bʌt]","backup":"[ˈbækʌp]","bottom":"[ˈbɒtəm]","before":"[bɪˈfɔː(r)]","between":"[bɪˈtwiːn]","box":"[bɒks]","by":"[baɪ]","byte":"[baɪt]","bypass":"[ˈbaɪpɑːs]","by first":"","by default":"","button":"[ˈbʌtn]","built-in":"[ˌbɪlt ˈɪn]","builder":"[ˈbɪldə(r)]","build":"[bɪld]","bug":"[bʌɡ]","buffering":"['bʌfərɪŋ]","buffered":"","buffer":"[ˈbʌfə(r)]","bucket":"[ˈbʌkɪt]","bubble":"[ˈbʌbl]","browser":"[ˈbraʊzə(r)]","browse":"[braʊz]","broker":"[ˈbrəʊkə(r)]","bridge":"[brɪdʒ]","break up":"","break…into..":"","break":"[breɪk]","brand":"[brænd]","brackets":"['brækɪts]","boundary":"[ˈbaʊndri]","bound with…":"","bound":"[baʊnd]","border":"[ˈbɔːdə(r)]","bootstrap":"['buːtstræp]","boolean":"[ˈbuːliən]","bone":"[bəʊn]","bomb":"[bɒm]","bold":"[bəʊld]","block statement":"","block":"[blɒk]","blank space":"","blank":"[blæŋk]","bind…to…":"","bind":"[baɪnd]","binary":"[ˈbaɪnəri]","bidirectional":"[ˌbaɪdəˈrekʃənl; ˌbaɪdaɪˈrekʃənl]","beyond the fact that…":"","beyond":"[bɪˈjɒnd]","benefit from…":"","behave":"[bɪˈheɪv]","behalf":"[bɪˈhɑːf]","bean":"[biːn]","be up to":"","be taken to":"","be subject to…":"","be of…":"","be aware to…":"","be all about…":"","batch":"[bætʃ]","best-effort basis":"","behavior":"[bɪˈheɪvjə]","beginning":"[bɪˈɡɪnɪŋ]","begin with…":"","beautification":"[,bjʊtɪfɪ'keʃən]","basic":"[ˈbeɪsɪk]","base":"[beɪs]","bar":"[bɑː(r)]","balance":"[ˈbæləns]","backward":"[ˈbækwəd]","backspace":"[ˈbækspeɪs]","backslash":"[ˈbækslæʃ]","backing":"[ˈbækɪŋ]","background":"[ˈbækɡraʊnd]","backend":"['bæk,ɛnd]","back":"[bæk]","combo":"[ˈkɒmbəʊ]","course":"[kɔːs]","charm":"[tʃɑːm]","circumstances":"","caret":"[ˈkærət]","clean":"[kliːn]","cad":"[kæd]","contiguous":"[kənˈtɪɡjuəs]","clipper":"[ˈklɪpə(r)]","consequently":"[ˈkɒnsɪkwəntli]","craze":"[kreɪz]","crop":"[krɒp]","continuously":"[kənˈtɪnjuəsli]","chart":"[tʃɑːt]","cross":"[krɒs]","complicated":"[ˈkɒmplɪkeɪtɪd]","creation":"[kriˈeɪʃn]","complex":"[ˈkɒmpleks]","contrast":"[ˈkɒntrɑːst]","constantly":"[ˈkɒnstəntli]","comprise":"[kəmˈpraɪz]","closely":"[ˈkləʊsli]","congratulation":"[kənˌɡrætʃuˈleɪʃn]","care":"[keə(r)]","consume":"[kənˈsjuːm]","capitalized":"['kæpɪtəlɑɪzd]","charge":"[tʃɑːdʒ]","certainty":"[ˈsɜːtnti]","cash":"[kæʃ]","commercial":"[kəˈmɜːʃl]","city":"[ˈsɪti]","classify":"[ˈklæsɪfaɪ]","choice":"[tʃɔɪs]","confidential":"[ˌkɒnfɪˈdenʃl]","criterion":"[kraɪˈtɪəriən]","conjunction":"[kənˈdʒʌŋkʃn]","customer":"[ˈkʌstəmə(r)]","calculation":"[ˌkælkjuˈleɪʃn]","cover":"[ˈkʌvə(r)]","clockwise":"[ˈklɒkwaɪz]","clock":"[klɒk]","conventional":"[kənˈvenʃənl]","critical":"[ˈkrɪtɪkl]","compress":"[kəmˈpres]","considered":"[kən'sɪdəd]","carousel":"[ˌkærəˈsel]","corrupt":"[kəˈrʌpt]","cycle":"[ˈsaɪkl]","central":"[ˈsentrəl]","cpu":"[ˌsiː piː ˈjuː]","certain":"[ˈsɜːtn]","converted":"[kən'vɜːtɪd]","correction":"[kəˈrekʃn]","controlled":"[kənˈtrəʊld]","correctly":"[kəˈrektli]","card":"[kɑːd]","combine":"[kəmˈbaɪn]","company":"[ˈkʌmpəni]","copyright":"[ˈkɒpiraɪt]","contact":"[ˈkɒntækt]","century":"[ˈsentʃəri]","come":"[kʌm]","consist":"[kənˈsɪst]","corner":"[ˈkɔːnə(r)]","calling":"[ˈkɔːlɪŋ]","computer":"[kəmˈpjuːtə(r)]","coprocessor":"['ko,prɑsɛsɚ]","carry":"[ˈkæri]","click":"[klɪk]","combination":"[ˌkɒmbɪˈneɪʃn]","continue":"[kənˈtɪnjuː]","check":"[tʃek]","carriage":"[ˈkærɪdʒ]","character":"[ˈkærəktə(r)]","cut":"[kʌt]","customized":"[ˈkʌstəmaɪzd]","customize":"[ˈkʌstəmaɪz]","custom":"[ˈkʌstəm]","cursor":"[ˈkɜːsə(r)]","currently":"[ˈkʌrəntli]","current":"[ˈkʌrənt]","currency":"[ˈkʌrənsi]","criteria":"[kraɪ'tɪərɪə]","credit":"[ˈkredɪt]","create":"[kriˈeɪt]","coverage":"[ˈkʌvərɪdʒ]","course of action":"","counterpart":"[ˈkaʊntəpɑːt]","counter":"[ˈkaʊntə(r)]","count":"[kaʊnt]","costly":"[ˈkɒstli]","cost":"[kɒst]","correspond to":"","corresponding":"[ˌkɒrəˈspɒndɪŋ]","correspond":"[ˌkɒrəˈspɒnd]","correctness":"[kəˈrektnəs]","correct":"[kəˈrekt]","copy":"[ˈkɒpi]","cookie":"[ˈkʊki]","converter":"[kənˈvɜːtə(r)]","convert":"[kənˈvɜːt]","conversion":"[kənˈvɜːʃn]","convention":"[kənˈvenʃn]","convenient":"[kənˈviːniənt]","convenience":"[kənˈviːniəns]","connectivity":"[kəˌnekˈtɪvəti]","connection":"[kəˈnekʃn]","controller":"[kənˈtrəʊlə(r)]","control":"[kənˈtrəʊl]","contrary":"['kɒntrərɪ]","contract":"[ˈkɒntrækt]","continue to…":"","context":"[ˈkɒntekst]","contention":"[kənˈtenʃn]","content":"[kən'tent]","container":"[kənˈteɪnə(r)]","contained":"[kən'teɪnd]","contain":"[kənˈteɪn]","consult":"[kənˈsʌlt]","construe":"[kənˈstruː]","constructor":"[kənˈstrʌktə(r)]","construct":"[kənˈstrʌkt]","constraint":"[kənˈstreɪnt]","constant":"[ˈkɒnstənt]","console":"[kən'səʊl]","consistent":"[kənˈsɪstənt]","consist of…":"","consideration":"[kənˌsɪdəˈreɪʃn]","consider":"[kənˈsɪdə(r)]","consecutive":"[kənˈsekjətɪv]","connection to…":"","connection with…":"","connect":"[kəˈnekt]","confuse":"[kənˈfjuːz]","conform":"[kənˈfɔːm]","conflict":"[ˈkɒnflɪkt]","confirmation":"[ˌkɒnfəˈmeɪʃn]","confirm":"[kənˈfɜːm]","configuration":"[kənˌfɪɡəˈreɪʃn]","configure":"[kənˈfɪɡə(r)]","conditional":"[kənˈdɪʃənl]","condition":"[kənˈdɪʃn]","concurrently":"[kənˈkʌrəntli]","concurrent":"[kənˈkʌrənt]","concrete":"[ˈkɒŋkriːt]","concise":"[kənˈsaɪs]","concerning":"[kənˈsɜːnɪŋ]","concept":"[ˈkɒnsept]","concatenation":"[kənˌkætəˈneɪʃn]","concatenate":"[kən'kætɪneɪt]","compute":"[kəmˈpjuːt]","compromised":"","compression":"[kəmˈpreʃn]","compound":"[ˈkɒmpaʊnd]","compose":"[kəmˈpəʊz]","component":"[kəmˈpəʊnənt]","comply":"[kəmˈplaɪ]","compliance":"[kəmˈplaɪəns]","complexity":"[kəmˈpleksəti]","completion":"[kəmˈpliːʃn]","completely":"[kəmˈpliːtli]","completed":"[kəm'plitɪd]","complete":"[kəmˈpliːt]","compiler":"[kəmˈpaɪlə(r)]","compile":"[kəmˈpaɪl]","compilation":"[ˌkɒmpɪˈleɪʃn]","compete":"[kəmˈpiːt]","compatible with...":"","compatible":"[kəmˈpætəbl]","compatibility":"[kəmˌpætəˈbɪləti]","comparison":"[kəmˈpærɪsn]","compare…to…":"","compare ...against":"","compare":"[kəmˈpeə(r)]","comparator":"[kəm'pærətə]","comparable":"[ˈkɒmpərəbl]","companion":"[kəmˈpænjən]","compact":"[kəmˈpækt; ˈkɒmpækt]","communication":"[kəˌmjuːnɪˈkeɪʃn]","communicate":"[kəˈmjuːnɪkeɪt]","commonly":"[ˈkɒmənli]","common":"[ˈkɒmən]","commit":"[kəˈmɪt]","comment":"[ˈkɒment]","command":"[kəˈmɑːnd]","comma":"[ˈkɒmə]","column":"[ˈkɒləm]","color":"[ˈkʌlə(r)]","colon":"[ˈkəʊlən; ˈkəʊlɒn]","collision":"[kəˈlɪʒn]","collectively":"[kəˈlektɪvli]","collection":"[kəˈlekʃn]","collapse":"[kəˈlæps]","coercion":"[kəʊˈɜːʃn]","coerce":"[kəʊˈɜːs]","code":"[kəʊd]","cock":"[kɒk]","clause":"[klɔːz]","closing":"[ˈkləʊzɪŋ]","closest":"[kləusɪst]","closed":"[kləʊzd]","close":"[kləʊs]","clone":"[kləʊn]","client":"[ˈklaɪənt]","clearly":"[ˈklɪəli]","clear":"[klɪə(r)]","cleanly":"[ˈkliːnli]","clean up…":"","class body":"","class":"[klɑːs]","circumstance":"[ˈsɜːkəmstəns; ˈsɜːkəmstɑːns; ˈsɜːkəmstæns]","circumference":"[səˈkʌmfərəns]","circle":"[ˈsɜːkl]","chunked encoding":"","chunk":"[tʃʌŋk]","chore":"[tʃɔː(r)]","choose":"[tʃuːz]","chick":"[tʃɪk]","checked":"[tʃekt]","checkbox":"[ˈtʃekbɒks]","charset":"","char":"[tʃɑː(r)]","chapter":"[ˈtʃæptə(r)]","chain":"[tʃeɪn]","change":"[tʃeɪndʒ]","certificate":"[səˈtɪfɪkət]","center":"[ˈsentə(r)]","ceil":"[siːl]","caution":"[ˈkɔːʃn]","cause":"[kɔːz]","cast":"[kɑːst]","case":"[keɪs]","cascade to…":"","cascade":"[kæˈskeɪd]","carriage return":"","captured":"","capture":"[ˈkæptʃə(r)]","capacity":"[kəˈpæsəti]","capable":"[ˈkeɪpəbl]","capability":"[ˌkeɪpəˈbɪləti]","canonical":"[kəˈnɒnɪkl]","cancel":"[ˈkænsl]","call stack":"","caller":"[ˈkɔːlə(r)]","callback":"[ˈkɔːlbæk]","call":"[kɔːl]","calculate":"[ˈkælkjuleɪt]","cache":"[kæʃ]","digital":"[ˈdɪdʒɪtl]","distinction":"[dɪˈstɪŋkʃn]","differentiate":"[ˌdɪfəˈrenʃieɪt]","desk":"[desk]","demonstrate":"[ˈdemənstreɪt]","deter":"[dɪˈtɜː(r)]","discussion":"[dɪˈskʌʃn]","diagonally":"[daɪˈæɡənəli]","disappear":"[ˌdɪsəˈpɪə(r)]","defective":"[dɪˈfektɪv]","definable":"[dɪˈfaɪnəbl]","disregard":"[ˌdɪsrɪˈɡɑːd]","daily":"[ˈdeɪli]","dearly":"[ˈdɪəli]","distribute":"[dɪˈstrɪbjuːt; ˈdɪstrɪbjuːt]","degrade":"[dɪˈɡreɪd]","difficulty":"[ˈdɪfɪkəlti]","deal":"[diːl]","desirable":"[dɪˈzaɪərəbl]","department":"[dɪˈpɑːtmənt]","differ":"[ˈdɪfə(r)]","difficult":"[ˈdɪfɪkəlt]","diacritical":"[ˌdaɪəˈkrɪtɪkl]","dimensional":"[daɪmenʃənl; dɪmenʃənl]","density":"[ˈdensəti]","death":"[deθ]","derelict":"[ˈderəlɪkt]","discuss":"[dɪˈskʌs]","decide":"[dɪˈsaɪd]","disconnect":"[ˌdɪskəˈnekt]","desktop":"[ˈdesktɒp]","door":"[dɔː(r)]","descend":"[dɪˈsend]","due":"[djuː]","damage":"[ˈdæmɪdʒ]","design":"[dɪˈzaɪn]","deactivate":"[diːˈæktɪveɪt]","dot":"[dɒt]","delay":"[dɪˈleɪ]","direction":"[dəˈrekʃn; daɪˈrekʃn]","determined":"[dɪˈtɜːmɪnd]","dual":"[ˈdjuːəl]","described":"[dɪ'skraɪbd]","day":"[deɪ]","describe":"[dɪˈskraɪb]","directly":"[dəˈrektli; daɪˈrektli]","demonstration":"[ˌdemənˈstreɪʃn]","during":"[ˈdjʊərɪŋ]","diskette":"[dɪsˈket]","dos":"[dɒs]","different":"[ˈdɪfrənt]","down":"[daʊn]","do":"[duː]","dynamical":"[daɪ'næmɪkəl]","dynamic":"[daɪˈnæmɪk]","drop-in":"[ˈdrɒp ɪn]","drivermanager":"","driver":"[ˈdraɪvə(r)]","drive":"[draɪv]","draw":"[drɔː]","drag":"[dræɡ]","duty":"[ˈdjuːti]","duration":"[djuˈreɪʃn]","duplicate":"[ˈdjuːplɪkeɪt]","dump":"[dʌmp]","due to…":"","download":"[daʊn'ləʊd]","downcasting":"","doubly":"[ˈdʌbli]","double":"[ˈdʌbl]","domain":"[dəˈmeɪn; dəʊˈmeɪn]","documentation":"[ˌdɒkjumenˈteɪʃn]","document":"[ˈdɒkjumənt]","division":"[dɪˈvɪʒn]","divide":"[dɪˈvaɪd]","distribution":"[ˌdɪstrɪˈbjuːʃn]","distributed":"[dɪ'strɪbjʊtɪd]","distinguish":"[dɪˈstɪŋɡwɪʃ]","distinct":"[dɪˈstɪŋkt]","display":"[dɪˈspleɪ]","disperse":"[dɪˈspɜːs]","dispatcher":"[dɪˈspætʃə(r)]","dispatching":"[dɪs'pætʃɪŋ]","dispatch":"[dɪˈspætʃ]","disk drive":"","disk":"[dɪsk]","discretion":"[dɪˈskreʃn]","discover":"[dɪˈskʌvə(r)]","discount":"['dɪskaʊnt]","discouraged":"[dɪsˈkʌrɪdʒd]","discard":"[dɪˈskɑːd]","disadvantage":"[ˌdɪsədˈvɑːntɪdʒ]","disabled":"[dɪsˈeɪbld]","disable":"[dɪsˈeɪbl]","directory":"[dəˈrektəri; daɪˈrektəri]","direct":"[dəˈrekt; daɪˈrekt]","dimension":"[daɪˈmenʃn; dɪˈmenʃn]","digit":"[ˈdɪdʒɪt]","difference":"[ˈdɪfrəns]","dictionary":"[ˈdɪkʃənri]","diameter":"[daɪˈæmɪtə(r)]","dialog":"['daɪəlɒɡ]","dialect":"[ˈdaɪəlekt]","device":"[dɪˈvaɪs]","development":"[dɪˈveləpmənt]","developer":"[dɪˈveləpə(r)]","develop":"[dɪˈveləp]","detractor":"[dɪˈtræktə(r)]","deterministic":"[dɪˌtɜːmɪˈnɪstɪk]","determine":"[dɪˈtɜːmɪn]","detect":"[dɪˈtekt]","detail":"[ˈdiːteɪl]","detached":"[dɪˈtætʃt]","destructive":"[dɪˈstrʌktɪv]","destroy":"[dɪˈstrɔɪ]","destination":"[ˌdestɪˈneɪʃn]","desired":"[dɪ'zaɪəd]","desire":"[dɪˈzaɪə(r)]","designated":"['dezɪɡ,neɪtɪd]","designate":"[ˈdezɪɡneɪt]","descriptor":"[dɪˈskrɪptə(r)]","description":"[dɪˈskrɪpʃn]","descendant":"[dɪˈsendənt]","derive":"[dɪˈraɪv]","deprecated":"[ˈdeprəkeɪtɪd]","deprecate":"[ˈdeprəkeɪt]","depth":"[depθ]","deployment":"[dɪˈplɔɪmənt]","dependent":"[dɪˈpendənt]","dependency":"[dɪˈpendənsi]","depend":"[dɪˈpend]","deny":"[dɪˈnaɪ]","denote":"[dɪˈnəʊt]","demo":"[ˈdeməʊ]","delimiting":"[diːˈlɪmɪt]","delimiter":"[dɪ'lɪmɪtə]","delimit":"[diːˈlɪmɪt]","deletion":"[dɪˈliːʃn]","delete":"[dɪˈliːt]","delegation":"[ˌdelɪˈɡeɪʃn]","delegate":"[ˈdelɪɡət]","definition":"[ˌdefɪˈnɪʃn]","defining":"[dɪˈfaɪnɪŋ]","defined":"[dɪˈfaɪnd]","define":"[dɪˈfaɪn]","defer":"[dɪˈfɜː(r)]","defaults":"","default":"[dɪˈfɔːlt; ˈdiːfɔːlt]","deep":"[diːp]","deem":"[diːm]","decrease":"[dɪ'kriːs]","decoration":"[ˌdekəˈreɪʃn]","decode":"","declared":"[dɪˈkleəd]","declare":"[dɪˈkleə(r)]","declaration":"[ˌdekləˈreɪʃn]","decision":"[dɪˈsɪʒn]","decimal":"[ˈdesɪml]","decay":"[dɪˈkeɪ]","debugging":"[diː'bʌɡɪŋ]","debugger":"[ˌdiːˈbʌɡə(r)]","debug":"[ˌdiːˈbʌɡ]","de facto":"","datum":"[ˈdeɪtəm]","date":"[deɪt]","datasource":"","database":"[ˈdeɪtəbeɪs; ˈdɑːtəbeɪs]","data":"[ˈdeɪtə; ˈdɑːtə]","exceeded":"[ɪk'si:dɪd]","esoteric":"[ˌiːsəˈterɪk; ˌesəˈterɪk]","equipment":"[ɪˈkwɪpmənt]","explanatory":"[ɪkˈsplænətri]","eventually":"[ɪˈventʃuəli]","effective":"[ɪˈfektɪv]","enjoy":"[ɪnˈdʒɔɪ]","equally":"[ˈiːkwəli]","employe":"[,emplɒɪ'iː]","executable":"[ˌeksɪˈkjuːtəbl]","emulation":"[ˌemjuˈleɪʃn]","equation":"[ɪˈkweɪʒn]","extremely":"[ɪkˈstriːmli]","exponential":"[ˌekspəˈnenʃl]","experiment":"[ɪkˈsperɪmənt]","experimentation":"[ɪkˌsperɪmenˈteɪʃn]","expunge":"[ɪkˈspʌndʒ]","effort":"[ˈefət]","endeavor":"[ɪn'devə]","ensemble":"[ɒnˈsɒmbl]","ever":"[ˈevə(r)]","employee":"[ɪmˈplɔɪiː]","emulate":"[ˈemjuleɪt]","emphasize":"[ˈemfəsaɪz]","extract":"[ˈekstrækt]","exclamation":"[ˌekskləˈmeɪʃn]","easel":"[ˈiːzl]","environmental":"[ɪnˌvaɪrənˈmentl]","elapsed":"","entirely":"[ɪnˈtaɪəli]","ending":"[ˈendɪŋ]","especially":"[ɪˈspeʃəli]","explanation":"[ˌekspləˈneɪʃn]","early":"[ˈɜːli]","explain":"[ɪkˈspleɪn]","easy":"[ˈiːzi]","emulator":"[ˈemjuleɪtə(r)]","easily":"[ˈiːzəli]","enough":"[ɪˈnʌf]","expansion":"[ɪkˈspænʃn]","expanding":"[ɪk'spændɪŋ]","echo":"[ˈekəʊ]","eject":"[ɪˈdʒekt]","every":"[ˈevri]","environ":"[ɪn'vaɪrən; en-]","edge":"[edʒ]","except":"[ɪkˈsept]","editor":"[ˈedɪtə(r)]","either":"[ˈaɪðə(r); ˈiːðə(r)]","erase":"[ɪˈreɪz]","end":"[end]","each":"[iːtʃ]","example":"[ɪɡˈzɑːmpl]","evolve":"[ɪˈvɒlv]","evict":"[ɪˈvɪkt]","extreme":"[ɪkˈstriːm]","extraction":"[ɪkˈstrækʃn]","extra":"[ˈekstrə]","external":"[ɪkˈstɜːnl]","extent":"[ɪkˈstent]","extension":"[ɪkˈstenʃn]","extensible":"[ek'stensɪbl; ɪk'stensɪb(ə)l]","extense":"[ik'stens]","extends":"[ɪk'stendz; ek-]","extend":"[ɪkˈstend]","expression":"[ɪkˈspreʃn]","express":"[ɪkˈspres]","expose":"[ɪkˈspəʊz]","exported":"","export":"[ɪkˈspɔːt]","exponent":"[ɪkˈspəʊnənt]","explorer":"[ɪkˈsplɔːrə(r)]","explore":"[ɪkˈsplɔː(r)]","explode":"[ɪkˈspləʊd]","explicitly":"[ɪkˈsplɪsɪtli]","explicit":"[ɪkˈsplɪsɪt]","expiry":"[ɪkˈspaɪəri]","expired":"[ɪkˈspaɪəd]","expire":"[ɪkˈspaɪə(r)]","experience":"[ɪkˈspɪəriəns]","expected":"[ɪkˈspektɪd]","expect":"[ɪkˈspekt]","expand":"[ɪkˈspænd]","exit":"[ˈeksɪt; ˈeɡzɪt]","existing":"[ɪɡˈzɪstɪŋ]","existence":"[ɪɡˈzɪstəns]","exist":"[ɪɡˈzɪst]","exhaustive":"[ɪɡˈzɔːstɪv]","exhaust":"[ɪɡˈzɔːst]","exercise care":"","execution":"[ˌeksɪˈkjuːʃn]","execute":"[ˈeksɪkjuːt]","exception":"[ɪkˈsepʃn]","exclusively":"[ɪkˈskluːsɪvli]","exclusive":"[ɪkˈskluːsɪv]","excluding":"[ɪkˈskluːdɪŋ]","exclude":"[ɪkˈskluːd]","exceed":"[ɪkˈsiːd]","excapexml":"","examine":"[ɪɡˈzæmɪn]","exactly":"[ɪɡˈzæktli]","exact":"[ɪɡˈzækt]","even":"[ˈiːvn]","evaluation":"[ɪˌvæljuˈeɪʃn]","evaluate":"[ɪˈvæljueɪt]","establish":"[ɪˈstæblɪʃ]","essentially":"[ɪˈsenʃəli]","essential":"[ɪˈsenʃl]","essence":"[ˈesns]","escaped":"[ɪˈskeɪpt]","escape":"[ɪˈskeɪp]","error":"[ˈerə(r)]","erasure of…":"","erasure":"[ɪˈreɪʒə(r)]","equivalent":"[ɪˈkwɪvələnt]","equivalence":"[ɪˈkwɪvələns]","equate":"[ɪˈkweɪt]","equal to...":"","equality":"[iˈkwɒləti]","equal":"[ˈiːkwəl]","environment":"[ɪnˈvaɪrənmənt]","enumeration":"[ɪˌnjuːməˈreɪʃn]","enumerate":"[ɪˈnjuːməreɪt]","entry":"[ˈentri]","entity":"[ˈentəti]","entire":"[ɪnˈtaɪə(r)]","enterprise":"[ˈentəpraɪz]","enter":"[ˈentə(r)]","ensure":"[ɪnˈʃʊə(r); ɪnˈʃɔː(r)]","enhance":"[ɪnˈhɑːns]","engine":"[ˈendʒɪn]","enforce":"[ɪnˈfɔːs]","endpoint":"['end,pɒɪnt]","encryption":"[ɪnˈkrɪpʃn]","encounter":"[ɪnˈkaʊntə(r)]","encode":"[ɪnˈkəʊd]","enclosing type":"","enclosing instance":"","enclose":"[ɪnˈkləʊz]","encapsulation":"[ɪnˌkæpsjuˈleɪʃn]","encapsulate":"[ɪnˈkæpsjuleɪt]","enable":"[ɪˈneɪbl]","empty":"[ˈempti]","emit":"[iˈmɪt]","embedded":"[ɪm'bedɪd]","embed":"[ɪmˈbed]","else":"[els]","ellipsis":"[ɪˈlɪpsɪs]","eliminate":"[ɪˈlɪmɪneɪt]","element":"[ˈelɪmənt]","elapse":"[ɪˈlæps]","ejection":"[ɪˈdʒekʃn]","efficiently":"[ɪˈfɪʃntli]","efficient":"[ɪˈfɪʃnt]","efficiency":"[ɪˈfɪʃnsi]","effectively":"[ɪˈfektɪvli]","effect":"[ɪˈfekt]","edit":"[ˈedɪt]","fundamental":"[ˌfʌndəˈmentl]","fourscore":"[fɔː'skɔː]","familiarize":"[fəˈmɪliəraɪz]","finisher":"[ˈfɪnɪʃər]","fly":"[flaɪ]","financial":"[faɪˈnænʃl; fəˈnænʃl]","formation":"[fɔːˈmeɪʃn]","father":"[ˈfɑːðə(r)]","fine":"[faɪn]","fancy":"[ˈfænsi]","forget":"[fəˈɡet]","familiar":"[fəˈmɪliə(r)]","fix":"[fɪks]","forced":"[fɔːst]","figure":"[ˈfɪɡə(r)]","foreground":"[ˈfɔːɡraʊnd]","finish":"[ˈfɪnɪʃ]","fifth":"[fɪfθ]","fall":"[fɔːl]","filing":"[ˈfaɪlɪŋ]","future":"[ˈfjuːtʃə(r)]","fastback":"['fɑːs(t)bæk]","fact":"[fækt]","front":"[frʌnt]","false":"[fɔːls]","freeze":"[friːz]","face":"[feɪs]","formed":"[fɔ:md]","far":"[fɑː(r)]","finished":"[ˈfɪnɪʃt]","frequently":"[ˈfriːkwəntli]","fit":"[fɪt]","floating":"[ˈfləʊtɪŋ]","fast":"[fɑːst]","floppy":"[ˈflɒpi]","fixed":"[fɪkst]","follow":"[ˈfɒləʊ]","filename":"[ˈfaɪlneɪm]","first":"[fɜːst]","from":"[frəm; frɒm]","furthermore":"[ˌfɜːðəˈmɔː(r)]","further":"[ˈfɜːðə(r)]","functionality":"[ˌfʌŋkʃəˈnæləti]","function":"[ˈfʌŋkʃn]","fully":"[ˈfʊli]","full":"[fʊl]","fulfill":"[fʊlˈfɪl]","from and to…":"","frequent":"['friːkw(ə)nt]","frequency":"[ˈfriːkwənsi]","free":"[friː]","framework":"[ˈfreɪmwɜːk]","frameset":"","frame":"[freɪm]","fragment":"['frægmənt]","fractional":"[ˈfrækʃənl]","fraction":"[ˈfrækʃn]","found":"[faʊnd]","forward":"[ˈfɔːwəd]","forth":"[fɔːθ]","formula":"[ˈfɔːmjələ]","former":"[ˈfɔːmə(r)]","formatting":"[fɔː'meɪtɪŋ]","formatter":"['fɔ:mætə]","formatted":"[fɔ:rmætid]","format...as…":"","format":"[ˈfɔːmæt]","formally":"[ˈfɔːməli]","formalize":"[ˈfɔːməlaɪz]","formal":"[ˈfɔːml]","form":"[fɔːm]","foregoing":"[ˈfɔːɡəʊɪŋ]","force":"[fɔːs]","forbid":"[fəˈbɪd]","for instance":"","font":"[fɒnt]","following":"[ˈfɒləʊɪŋ]","folder":"[ˈfəʊldə(r)]","flush":"[flʌʃ]","floor":"[flɔː(r)]","floated":"['fləutid]","float":"[fləʊt]","flag":"[flæɡ]","fit in…":"","find":"[faɪnd]","finally":"[ˈfaɪnəli]","finalize":"[ˈfaɪnəlaɪz]","final":"[ˈfaɪnl]","filtering":"['fɪltərɪŋ]","filter":"[ˈfɪltə(r)]","fill":"[fɪl]","file":"[faɪl]","field":"[fiːld]","fetch":"[fetʃ]","feed":"[fiːd]","feature":"[ˈfiːtʃə(r)]","fashion":"[ˈfæʃn]","family":"[ˈfæməli]","failure to…":"","failure":"[ˈfeɪljə(r)]","fail-fast":"","fail":"[feɪl]","factory":"[ˈfæktri; ˈfæktəri]","factorial":"[fækˈtɔːriəl]","factor":"[ˈfæktə(r)]","facility":"[fəˈsɪləti]","gain":"[ɡeɪn]","growing":"[ˈɡrəʊɪŋ]","glance":"[ɡlɑːns]","guard":"[ɡɑːd]","greatly":"[ˈɡreɪtli]","glass":"[ɡlɑːs]","gap":"[ɡæp]","grey":"[ɡreɪ]","graphically":"[ˈɡræfɪkli]","green":"[ɡriːn]","gather":"[ˈɡæðə(r)]","global":"[ˈɡləʊbl]","greater":"[greɪtə(r)]","give":"[ɡɪv]","graphic":"[ˈɡræfɪk]","go":"[ɡəʊ]","guide":"[ɡaɪd]","guaranteed":"[ˌɡærənˈtiːd]","guarantee":"[ˌɡærənˈtiː]","growth":"[ɡrəʊθ]","growable":"['grəuəbl]","grouping":"[ˈɡruːpɪŋ]","group":"[ɡruːp]","grid":"[ɡrɪd]","greedy":"[ˈɡriːdi]","graph":"[ɡrɑːf]","grant":"[ɡrɑːnt]","grammar":"[ˈɡræmə(r)]","gnaw":"[nɔː]","giving":"['ɡɪvɪŋ]","given":"[ˈɡɪvn]","give a view into…":"","gird":"[ɡɜːd]","getter":"['getə]","get":"[ɡet]","gender":"[ˈdʒendə(r)]","generic":"[dʒəˈnerɪk]","generator":"[ˈdʒenəreɪtə(r)]","generation":"[ˌdʒenəˈreɪʃn]","generated":"['dʒenə,reɪtɪd]","generate":"[ˈdʒenəreɪt]","generally speaking":"","generally":"[ˈdʒenrəli]","generalized":"[ˈdʒenrəlaɪzd]","generality":"[ˌdʒenəˈræləti]","general-purpose":"[ˌdʒenrəl ˈpɜːpəs]","general":"[ˈdʒenrəl]","garbage collected":"","garbage":"[ˈɡɑːbɪdʒ]","gateway":"[ˈɡeɪtweɪ]","hit":"[hɪt]","hang":"[hæŋ]","higher":"[ˈhaɪə(r)]","happening":"[ˈhæpənɪŋ]","hardly":"[ˈhɑːdli]","habit":"[ˈhæbɪt]","hand":"[hænd]","hundred":"[ˈhʌndrəd]","halfway":"[ˌhɑːfˈweɪ]","holding":"[ˈhəʊldɪŋ]","happen":"[ˈhæpən]","hercules":"['hə:kjuli:z]","helpful":"[ˈhelpfl]","hot":"[hɒt]","hex":"[heks]","half":"[hɑːf]","hyphen":"[ˈhaɪfn]","huge":"[hjuːdʒ]","horizontally":"[ˌhɒrɪˈzɒntəli]","here":"[hɪə(r)]","high":"[haɪ]","hello":"[həˈləʊ]","hardware":"[ˈhɑːdweə(r)]","hard":"[hɑːd]","home":"[həʊm]","history":"[ˈhɪstri]","how":"[haʊ]","help":"[help]","human":"[ˈhjuːmən]","however":"[haʊˈevə(r)]","hover":"[ˈhɒvə(r)]","host":"[həʊst]","horizontal":"[ˌhɒrɪˈzɒntl]","honest":"[ˈɒnɪst]","holdability":"","hold":"[həʊld]","hint":"[hɪnt]","highlight":"[ˈhaɪlaɪt]","highest":"[haɪɪst]","hierarchy":"[ˈhaɪərɑːki]","hierarchical":"[ˌhaɪəˈrɑːkɪkl]","hidden":"['hɪdn]","hide":"[haɪd]","hexadecimal":"[ˌheksəˈdesɪml]","hence":"[hens]","hen":"[hen]","height":"[haɪt]","hedge":"[hedʒ]","heap":"[hiːp]","heading":"[ˈhedɪŋ]","header":"[ˈhedə(r)]","head":"[hed]","hazardous":"[ˈhæzədəs]","have access to…":"","has no direct effect on…":"","hash":"[hæʃ]","handling":"[ˈhændlɪŋ]","handler":"[ˈhændlə(r)]","handle":"[ˈhændl]","hand-code":"","iterative":"[ˈɪtərətɪv]","infinite":"[ˈɪnfɪnət]","importance":"[ɪmˈpɔːtns]","indefinitely":"[ɪnˈdefɪnətli]","interest":"[ˈɪntrəst; ˈɪntrest]","interpretable":"[ɪnˈtɜːrprətəbl]","independently":"[ˌɪndɪˈpendəntli]","initiate":"[ɪˈnɪʃieɪt]","idea":"[aɪˈdɪə]","inexperienced":"[ˌɪnɪkˈspɪriənst]","invent":"[ɪnˈvent]","insure":"[ɪnˈʃʊə(r); ɪnˈʃɔː(r)]","intervene":"[ˌɪntəˈviːn]","interpretability":"","insufficient":"[ˌɪnsəˈfɪʃnt]","individually":"[ˌɪndɪˈvɪdʒuəli]","interfere":"[ˌɪntəˈfɪə(r)]","inverse":"[ˌɪnˈvɜːs]","industry":"[ˈɪndəstri]","identically":"[aɪˈdentɪkli]","inhibit":"[ɪnˈhɪbɪt]","instruct":"[ɪnˈstrʌkt]","icon":"[ˈaɪkɒn]","indicator":"[ˈɪndɪkeɪtə(r)]","involve":"[ɪnˈvɒlv]","increase":"[ɪn'kriːs]","important":"[ɪmˈpɔːtnt]","intend":"[ɪnˈtend]","integrate":"[ˈɪntɪɡreɪt]","intensity":"[ɪnˈtensəti]","intense":"[ɪnˈtens]","immediately":"[ɪˈmiːdiətli]","installation":"[ˌɪnstəˈleɪʃn]","interpreter":"[ɪnˈtɜːprətə(r)]","instead":"[ɪnˈsted]","issue":"[ˈɪʃuː; ˈɪsjuː]","into":"[ˈɪntə; ˈɪntu; ˈɪntuː]","if":"[ɪf]","iterator":"[ɪtə'reɪtə]","iteration":"[ˌɪtəˈreɪʃn]","iterate over…":"","iterate":"[ˈɪtəreɪt]","interact with…":"","item":"[ˈaɪtəm]","italic":"[ɪˈtælɪk]","it is good practice to":"","isolation":"[ˌaɪsəˈleɪʃn]","is said to…":"","is referred to as…":"","is not required to":"","is meant for…":"","is interleaved with...":"","is free to…":"","is closer to…":"","involved":"[ɪnˈvɒlvd]","invoke":"[ɪnˈvəʊk]","invocation":"[ˌɪnvəˈkeɪʃn]","invocate":"['ɪnvəʊkeɪt]","inversion":"[ɪnˈvɜːʃn]","invariant":"[ɪnˈveəriənt]","invalidated":"","invalidate":"[ɪnˈvælɪdeɪt]","invalid":"[ɪnˈvælɪd]","introduction":"[ˌɪntrəˈdʌkʃn]","introduce":"[ˌɪntrəˈdjuːs]","interval":"[ˈɪntəvl]","intersection":"[ˌɪntəˈsekʃn]","interrupted":"[ɪntə'rʌptɪd]","interrupt":"[ˌɪntəˈrʌpt]","interpret":"[ɪnˈtɜːprət]","internally":"[ɪnˈtɜːnəli]","internal":"[ɪnˈtɜːnl]","intern":"['ɪntɜːn]","intermix with…":"","interoperability":"[ˌɪntərˌɒpərəˈbɪləti]","interleave":"[ˌɪntəˈliːv]","interfer":"","interface":"[ˈɪntəfeɪs]","interactive":"[ˌɪntərˈæktɪv]","intentionally":"[ɪnˈtenʃənəli]","intended":"[ɪnˈtendɪd]","integrity":"[ɪnˈteɡrəti]","integrated":"[ˈɪntɪɡreɪtɪd]","integer":"[ˈɪntɪdʒə(r)]","instruction":"[ɪnˈstrʌkʃn]","instead of…":"","instantiation":"[ɪnstænʃɪ'eɪʃən]","instantiate":"[ɪn'stænʃɪeɪt]","instant":"[ˈɪnstənt]","instance":"[ˈɪnstəns]","install":"[ɪnˈstɔːl]","inside":"[ˌɪnˈsaɪd]","insertion point":"","insertion":"[ɪnˈsɜːʃn]","insert":"[ɪnˈsɜːt]","insensitive":"[ɪnˈsensətɪv]","inquire":"[ɪn'kwaɪə]","input source":"","input":"[ˈɪnpʊt]","inner":"[ˈɪnə(r)]","injection":"[ɪnˈdʒekʃn]","inject":"[ɪnˈdʒekt]","initializer":"[i'niʃəlaizə]","initialize":"[ɪˈnɪʃəlaɪz]","initialization":"[ɪˌnɪʃəlaɪˈzeɪʃn]","initially":"[ɪˈnɪʃəli]","initial":"[ɪˈnɪʃl]","infer":"[ɪnˈfɜː(r)]","indication":"[ˌɪndɪˈkeɪʃn]","inherited":"[ɪn'herɪtɪd]","inheritance":"[ɪnˈherɪtəns]","inherit":"[ɪnˈherɪt]","inherently":"[ɪnˈherəntli; ɪnˈhɪərəntli]","inherent":"[ɪnˈherənt; ɪnˈhɪərənt]","informative":"[ɪnˈfɔːmətɪv]","information":"[ˌɪnfəˈmeɪʃn]","infinity":"[ɪnˈfɪnəti]","ineligible":"[ɪnˈelɪdʒəbl]","individual":"[ˌɪndɪˈvɪdʒuəl]","indistinguishable":"[ˌɪndɪˈstɪŋɡwɪʃəbl]","indirectly":"[ˌɪndəˈrektli; ˌɪndaɪˈrektli]","indice":"['ɪndɪs]","indicated":"['ɪndə,keɪtɪd]","indicate":"[ˈɪndɪkeɪt]","indexing through":"","indexing":"['ɪndɛks]","index":"[ˈɪndeks]","independently of..":"","independent":"[ˌɪndɪˈpendənt]","indentation":"[ˌɪndenˈteɪʃn]","indent":"[ɪn'dent]","idempotent":"[,aɪdem'pəʊt(ə)nt; aɪ'dempət(ə)nt]","incremental":"[,ɪnkrɪ'mentəl]","increment":"[ˈɪŋkrəmənt]","incredibly":"[ɪnˈkredəbli]","incorrect":"[ˌɪnkəˈrekt]","incorporate":"[ɪnˈkɔːpəreɪt]","inconceivable":"[ˌɪnkənˈsiːvəbl]","incompatible":"[ˌɪnkəmˈpætəbl]","inclusive":"[ɪnˈkluːsɪv]","include":"[ɪnˈkluːd]","inclined":"[ɪnˈklaɪnd]","inactive":"[ɪnˈæktɪv]","in the face of…":"","in the case of…":"","in the absence of..":"","in that":"","in terms of":"","in sequence":"","in progress":"","in preference to…":"","in place of":"","in place":"","in particular":"","in other words":"","in order for…":"","in order":"","in-memory":"","in exactly":"","in essense":"","in effect":"","in contrast to..":"","in addition to…":"","improve":"[ɪmˈpruːv]","impose":"[ɪmˈpəʊz]","import":"[ˈɪmpɔːt]","imply":"[ɪmˈplaɪ]","implicitly":"[ɪmˈplɪsɪtli]","implicit":"[ɪmˈplɪsɪt]","implementor":"['implimentə]","implemented":"","implementation":"[ˌɪmplɪmenˈteɪʃn]","implement":"['ɪmplɪm(ə)nt]","immutable":"[ɪˈmjuːtəbl]","immediately following…":"","immediate":"[ɪˈmiːdiət]","imitate":"[ˈɪmɪteɪt]","image":"[ˈɪmɪdʒ]","illustrate":"[ˈɪləstreɪt]","illegal":"[ɪˈliːɡl]","ignore":"[ɪɡˈnɔː(r)]","idiom":"[ˈɪdiəm]","identity":"[aɪˈdentəti]","identify":"[aɪˈdentɪfaɪ]","identification":"[aɪˌdentɪfɪˈkeɪʃn]","identifier":"[aɪˈdentɪfaɪə(r)]","identical":"[aɪˈdentɪkl]","isconnecting":"","job":"[dʒɒb]","jump":"[dʒʌmp]","just":"[dʒʌst]","join":"[dʒɔɪn]","junior":"[ˈdʒuːniə(r)]","january":"[ˈdʒænjuəri]","keyed":"[kiːd]","kilobyte":"[ˈkɪləbaɪt]","kernel":"[ˈkɜːnl]","kind":"[kaɪnd]","keep":"[kiːp]","keypad":"[ˈkiːpæd]","know":"[nəʊ]","keyboard":"[ˈkiːbɔːd]","known as…":"","kit":"[kɪt]","keyword":"[ˈkiːwɜːd]","key":"[kiː]","keep track of":"","lending":"[ˈlendɪŋ]","limiter":"['lɪmətɚ]","logarithm":"[ˈlɒɡərɪðəm]","labeled":"['leibld]","logged":"['lɒɡd]","landler":"","lose":"[luːz]","limitations":"[,lɪmə'teʃən]","legal":"[ˈliːɡl]","low":"[ləʊ]","lightning":"[ˈlaɪtnɪŋ]","lot":"[lɒt]","limiting":"[ˈlɪmɪtɪŋ]","lesson":"[ˈlesn]","little":"[ˈlɪtl]","limited":"[ˈlɪmɪtɪd]","lexical":"[ˈleksɪkl]","layer":"[ˈleɪə(r); leə(r)]","locating":"[ləʊ'keɪtɪŋ]","least":"[liːst]","limit":"[ˈlɪmɪt]","let":"[let]","learning":"[ˈlɜːnɪŋ]","less":"[les]","loss":"[lɒs]","linker":"['lɪŋkɚ]","later":"[ˈleɪtə(r)]","lock":"[lɒk]","learn":"[lɜːn]","look":"[lʊk]","leave":"[liːv]","last":"[lɑːst]","lowest":"[ləʊɪst]","lowercase":"[,ləʊə'keɪs]","lower":"['ləʊə]","loop":"[luːp]","lookup":"['lʊkʌp]","long":"[lɒŋ]","login":"[ˈlɒɡɪn]","logical":"[ˈlɒdʒɪkl]","logic":"[ˈlɒdʒɪk]","logging":"[ˈlɒɡɪŋ]","log":"[lɒɡ]","locking":"['lɒkɪŋ]","location":"[ləʊˈkeɪʃn]","located":"[ləʊˈkeɪtɪd]","locate":"[ləʊˈkeɪt]","localized":"[ˈləʊkəlaɪzd]","localize":"[ˈləʊkəlaɪz]","locale":"[ləʊˈkɑːl]","local variable":"","local":"[ˈləʊkl]","loading":"[ˈləʊdɪŋ]","loader":"['ləʊdə]","loaded":"[ˈləʊdɪd]","load":"[ləʊd]","literal":"[ˈlɪtərəl]","listing":"[ˈlɪstɪŋ]","list":"[lɪst]","linked":"[lɪŋkt]","linkage":"[ˈlɪŋkɪdʒ]","link":"[lɪŋk]","linear":"[ˈlɪniə(r)]","line feed":"","line":"[laɪn]","limitation":"[ˌlɪmɪˈteɪʃn]","likewise":"[ˈlaɪkwaɪz]","likelihood":"[ˈlaɪklihʊd]","like":"[laɪk]","lighter":"[ˈlaɪtə(r)]","light":"[laɪt]","life-cycle":"[ˈlaɪf saɪkl]","library":"[ˈlaɪbrəri; ˈlaɪbri]","lexicographical":"[,leksikəu'ɡræfikəl]","lexicographic":"[,lɛksɪkə'græfɪk]","level":"[ˈlevl]","letter":"[ˈletə(r)]","lengthen":"[ˈleŋθən]","length":"[leŋθ]","legacy":"[ˈleɡəsi]","left":"[left]","leaving":"['liːvɪŋ]","leaf":"[liːf]","leading":"['liːdɪŋ]","layout":"[ˈleɪaʊt]","launcher":"[ˈlɔːntʃə(r)]","launch":"[lɔːntʃ]","latter":"[ˈlætə(r)]","larger":"[lɑ:dʒə(r)]","large":"[lɑːdʒ]","language":"[ˈlæŋɡwɪdʒ]","label":"[ˈleɪbl]","motif":"[məʊˈtiːf]","mixture":"[ˈmɪkstʃə(r)]","multiprocessing":"[mʌltɪ'prəʊsesɪŋ]","mountain":"[ˈmaʊntən]","masking":"['mɑːskɪŋ]","manipulating":"[mə'nɪpjə,let]","moment":"[ˈməʊmənt]","major":"[ˈmeɪdʒə(r)]","meter":"[ˈmiːtə(r)]","moreover":"[mɔːrˈəʊvə(r)]","magic":"[ˈmædʒɪk]","mismatch":"[ˌmɪsˈmætʃ]","mod":"[mɒd]","manufacture":"[ˌmænjuˈfæktʃə(r)]","mach":"[mɑːk,mæk]","mega":"[ˈmeɡə]","manually":"[ˈmænjuəli]","mind":"[maɪnd]","micro":"[ˈmaɪkrəʊ]","mainframe":"[ˈmeɪnfreɪm]","meaning":"[ˈmiːnɪŋ]","market":"[ˈmɑːkɪt]","medium":"[ˈmiːdiəm]","manifest":"[ˈmænɪfest]","meet":"[miːt]","mono":"[ˈmɒnəʊ]","midnight":"[ˈmɪdnaɪt]","matter":"[ˈmætə(r)]","middle":"[ˈmɪdl]","movement":"[ˈmuːvmənt]","murder":"[ˈmɜːdə(r)]","magenta":"[məˈdʒentə]","means":"[miːnz]","mixed":"[mɪkst]","movie":"[ˈmuːvi]","minimum":"[ˈmɪnɪməm]","mistake":"[mɪˈsteɪk]","month":"[mʌnθ]","mirror":"[ˈmɪrə(r)]","much":"[mʌtʃ]","marking":"[ˈmɑːkɪŋ]","macros":"['mækrɔs]","minus":"[ˈmaɪnəs]","monochrome":"[ˈmɒnəkrəʊm]","module":"[ˈmɒdjuːl]","memo":"[ˈmeməʊ]","matching":"[ˈmætʃɪŋ]","making":"[ˈmeɪkɪŋ]","math":"[mæθ]","moving":"[ˈmuːvɪŋ]","many":"[ˈmeni]","multi":"[ˈmʌlti]","mouse":"[maʊs]","macro":"[ˈmækrəʊ]","make":"[meɪk]","mode":"[məʊd]","marked":"[mɑːkt]","move":"[muːv]","mutually":"[ˈmjuːtʃuəli]","mutual":"[ˈmjuːtʃuəl]","mutate":"[mjuːˈteɪt]","mutable":"[ˈmjuːtəbl]","multithreaded":"","multiplicity":"[ˌmʌltɪˈplɪsəti]","multiplication":"[ˌmʌltɪplɪˈkeɪʃn]","multiple":"[ˈmʌltɪpl]","multipart":"","move up":"","mostly":"[ˈməʊstli]","more so":"","more formally":"","monolithic":"[ˌmɒnəˈlɪθɪk]","monitor":"[ˈmɒnɪtə(r)]","modify":"[ˈmɒdɪfaɪ]","modifier":"[ˈmɒdɪfaɪə(r)]","modified":"[ˈmɒdɪfaɪd]","modification":"[ˌmɒdɪfɪˈkeɪʃn]","modifiable":"['mɒdɪ,faɪəbl]","model":"[ˈmɒdl]","modal":"[ˈməʊdl]","mobile":"[ˈməʊbaɪl]","missing":"[ˈmɪsɪŋ]","missile":"[ˈmɪsaɪl]","minux":"","minimize":"[ˈmɪnɪmaɪz]","mine":"[maɪn]","millisecond":"[ˈmɪlisekənd]","migrate":"[maɪˈɡreɪt]","method":"[ˈmeθəd]","meta":"[ˈmetə]","message":"[ˈmesɪdʒ]","mergesort":"","merge":"[mɜːdʒ]","merely":"[ˈmɪəli]","menu":"[ˈmenjuː]","mention":"[ˈmenʃn]","memory":"[ˈmeməri]","member":"[ˈmembə(r)]","media":"[ˈmiːdiə]","mechanism":"[ˈmekənɪzəm]","meaningful":"[ˈmiːnɪŋfl]","mean":"[miːn]","measure to…":"","maximum":"[ˈmæksɪməm]","maximize":"[ˈmæksɪmaɪz]","maximal":"[ˈmæksɪml]","max":"[mæks]","matrix":"[ˈmeɪtrɪks]","mathematical":"[ˌmæθəˈmætɪkl]","materialize":"[məˈtɪəriəlaɪz]","matches":"['mætʃɪz]","matcher":"['mætʃə]","match…with…":"","match…against…":"","match":"[mætʃ]","master":"[ˈmɑːstə(r)]","mask":"[mɑːsk]","markup":"[ˈmɑːkʌp]","marker":"[ˈmɑːkə(r)]","mark":"[mɑːk]","margin":"[ˈmɑːdʒɪn]","mapping":"[ˈmæpɪŋ]","mapped":"","mappable":"['mæpəbl]","map…to…":"","map":"[mæp]","manual":"[ˈmænjuəl]","manner":"[ˈmænə(r)]","manipulation":"[məˌnɪpjuˈleɪʃn]","manipulate":"[məˈnɪpjuleɪt]","mandated":"[ˈmændeɪtɪd]","mandate":"[ˈmændeɪt]","manager":"[ˈmænɪdʒə(r)]","manage":"[ˈmænɪdʒ]","management":"[ˈmænɪdʒmənt]","mammal":"[ˈmæml]","malformed":"[ˌmælˈfɔːrmd]","mal-":"[mæl]","make use of…":"","make up…":"","maintain":"[meɪnˈteɪn]","main function":"","main":"[meɪn]","mail":"[meɪl]","machine":"[məˈʃiːn]","national":"[ˈnæʃnəl]","nature":"[ˈneɪtʃə(r)]","never":"[ˈnevə(r)]","nothing":"[ˈnʌθɪŋ]","noninteractive":"['nɔnintə'æktiv]","nicety":"[ˈnaɪsəti]","negate":"[nɪˈɡeɪt]","numerous":"[ˈnjuːmərəs]","noted":"[ˈnəʊtɪd]","nearly":"[ˈnɪəli]","neither":"[ˈnaɪðə(r); ˈniːðə(r)]","nor":"[nɔː(r)]","newly":"[ˈnjuːli]","necessary":"[ˈnesəsəri]","normal":"[ˈnɔːml]","network":"[ˈnetwɜːk]","navigation":"[ˌnævɪˈɡeɪʃn]","now":"[naʊ]","need":"[niːd]","next":"[nekst]","numerical":"[njuːˈmerɪkl]","numeric":"[njuː'merɪk]","numeral":"[ˈnjuːmərəl]","number":"[ˈnʌmbə(r)]","nullary":"","null":"[nʌl]","notion":"[ˈnəʊʃn]","notify":"[ˈnəʊtɪfaɪ]","notification":"[ˌnəʊtɪfɪˈkeɪʃn]","note":"[nəʊt]","notation":"[nəʊˈteɪʃn]","normative":"[ˈnɔːmətɪv]","normally":"[ˈnɔːməli]","normalized":"[ˈnɔrməˌlaɪzd]","normalize":"[ˈnɔːməlaɪz]","nonexistent":"[,nɑnɪg'zɪstənt]","no point in…":"","newline":"","nesting":"['nestɪŋ]","nested":"['nestɪd]","nest":"[nest]","negative":"[ˈneɡətɪv]","negation":"[nɪˈɡeɪʃn]","necessarily":"[ˌnesəˈserəli; ˈnesəsərəli]","nearest":"['nɪərɪst]","near":"[nɪə(r)]","navigator":"[ˈnævɪɡeɪtə(r)]","navigate":"[ˈnævɪɡeɪt]","navigable":"[ˈnævɪɡəbl]","naturally":"[ˈnætʃrəli]","natural":"[ˈnætʃrəl]","native":"[ˈneɪtɪv]","narrowing":"['næro]","nanosecond":"[ˈnænəʊsekənd]","namespace":"['neimspeis]","namely":"[ˈneɪmli]","named":"[nemd]","name":"[neɪm]","opinion":"[əˈpɪnjən]","outcome":"[ˈaʊtkʌm]","occupy":"[ˈɒkjupaɪ]","occasionally":"[əˈkeɪʒnəli]","ones":"[wʌnz]","overstrike":"['ovəstraɪk]","organization":"[ˌɔːɡənaɪˈzeɪʃn]","odometer":"[əʊˈdɒmɪtə(r)]","office":"[ˈɒfɪs]","overwrite":"[ˌəʊvəˈraɪt]","opposite":"[ˈɒpəzɪt; ˈɒpəsɪt]","often":"[ˈɒfn; ˈɒftən]","opened":"['opən]","organize":"[ˈɔːɡənaɪz]","own":"[əʊn]","over":"[ˈəʊvə(r)]","on-line":"[ɒnlaɪn]","onto":"[ˈɒntə; ˈɒntu]","opening":"[ˈəʊpənɪŋ]","overlay":"[ˌəʊvəˈleɪ]","once":"[wʌns]","out":"[aʊt]","ok":"[əʊˈkeɪ]","other":"[ˈʌðə(r)]","open":"[ˈəʊpən]","only":"[ˈəʊnli]","off":"[ɒf]","on":"[ɒn]","ownership":"[ˈəʊnəʃɪp]","owner":"[ˈəʊnə(r)]","overview":"[ˈəʊvəvjuː]","overriding":"[ˌəʊvəˈraɪdɪŋ]","override":"[ˌəʊvəˈraɪd]","overly":"[ˈəʊvəli]","overload":"[ˌəʊvəˈləʊd]","overhead":"[əʊvə'hed]","overflow":"[ˌəʊvəˈfləʊ]","overall":"['əʊvərɔːl]","over time":"","outside…":"[ˌaʊtˈsaɪd]","outputter":"","output":"[ˈaʊtpʊt]","outline":"[ˈaʊtlaɪn]","otherwise":"[ˈʌðəwaɪz]","other than":"","originate":"[əˈrɪdʒɪneɪt]","originally":"[əˈrɪdʒənəli]","original":"[əˈrɪdʒənl]","origin":"[ˈɒrɪdʒɪn]","oriented":"['ɔːrɪentɪd]","orient":"[ˈɔːrient]","ordinal":"[ˈɔːdɪnl]","ordering":"[ˈɔːdərɪŋ]","order":"[ˈɔːdə(r)]","optional":"[ˈɒpʃənl]","option":"[ˈɒpʃn]","optimize":"[ˈɒptɪmaɪz]","optimization":"[,ɒptɪmaɪ'zeɪʃən]","opportunity":"[ˌɒpəˈtjuːnəti]","operator":"[ˈɒpəreɪtə(r)]","operation":"[ˌɒpəˈreɪʃn]","operating":"['ɒpəreɪtɪŋ]","operate":"[ˈɒpəreɪt]","operand":"[ˈɒpərænd]","one for each":"","on one’s behalf":"","on-demand":"[ˌɑːn dɪˈmænd]","once again":"","on…":"[ɒn]","omit":"[əˈmɪt]","offset":"[ˈɒfset]","offer":"[ˈɒfə(r)]","of the sort…":"","odd":"[ɒd]","occurrence":"[əˈkʌrəns]","occur":"[əˈkɜː(r)]","obtain":"[əbˈteɪn]","obsolete":"[ˈɒbsəliːt]","observable":"[əbˈzɜːvəbl]","observe":"[əbˈzɜːv]","object":"[ˈɒbdʒɪkt]","obey":"[əˈbeɪ]","onstitute":"","ompiled":"","progress":"[ˈprəʊɡres]","please":"[pliːz]","pool":"[puːl]","photograph":"[ˈfəʊtəɡrɑːf]","predict":"[prɪˈdɪkt]","phrase":"[freɪz]","procedural":"[prəˈsiːdʒərəl]","printable":"[ˈprɪntəbl]","possibility":"[ˌpɒsəˈbɪləti]","programmable":"[prəʊˈɡræməbl; ˈprəʊɡræməbl]","probable":"[ˈprɒbəbl]","potentially":"[pəˈtenʃəli]","possibly":"[ˈpɒsəbli]","purpose":"[ˈpɜːpəs]","powerful":"[ˈpaʊəfl]","placement":"[ˈpleɪsmənt]","prefer":"[prɪˈfɜː(r)]","primary":"[ˈpraɪməri]","proprietary":"[prəˈpraɪətri]","protection":"[prəˈtekʃn]","parallel":"[ˈpærəlel]","printout":"[ˈprɪntaʊt]","purchase":"[ˈpɜːtʃəs]","purge":"[pɜːdʒ]","phone":"[fəʊn]","pseudo":"[ˈsuːdəʊ; ˈsjuːdəʊ]","preset":"[ˌpriːˈset]","pair":"[peə(r)]","particularly":"[pəˈtɪkjələli]","permanent":"[ˈpɜːmənənt]","pacific":"[pəˈsɪfɪk]","prepare":"[prɪˈpeə(r)]","piece":"[piːs]","pay":"[peɪ]","phoenix":"[ˈfiːnɪks]","permanently":"[ˈpɜːmənəntli]","picture":"[ˈpɪktʃə(r)]","processor":"[ˈprəʊsesə(r)]","publisher":"[ˈpʌblɪʃə(r)]","play":"[pleɪ]","product":"[ˈprɒdʌkt]","parenthesis":"[pəˈrenθəsɪs]","payment":"[ˈpeɪmənt]","preview":"[ˈpriːvjuː]","people":"[ˈpiːpl]","pause":"[pɔːz]","pertain":"[pəˈteɪn]","personal":"[ˈpɜːsənl]","pressed":"[prest]","paper":"[ˈpeɪpə(r)]","pack":"[pæk]","possible":"[ˈpɒsəbl]","put":"[pʊt]","past":"[pɑːst]","part":"[pɑːt]","practice":"[ˈpræktɪs]","positioning":"[pəˈzɪʃənɪŋ]","paragraph":"[ˈpærəɡrɑːf]","printer":"[ˈprɪntə(r)]","pressing":"[ˈpresɪŋ]","press":"[pres]","put forth":"","push":"[pʊʃ]","pure":"[pjʊə(r)]","public":"[ˈpʌblɪk]","pseudorandom":"[,sjuːdəʊ'rændəm]","proxied":"","proxy":"[ˈprɒksi]","provoke":"[prəˈvəʊk]","province":"[ˈprɒvɪns]","provide…for…":"","provide":"[prəˈvaɪd]","prototype":"[ˈprəʊtətaɪp]","protocol":"[ˈprəʊtəkɒl]","protected":"[prə'tektɪd]","protect":"[prəˈtekt]","proportional to…":"","property":"[ˈprɒpəti]","properly":"[ˈprɒpəli]","proper":"[ˈprɒpə(r)]","propagation":"[ˌprɒpəˈɡeɪʃn]","propagate":"[ˈprɒpəɡeɪt]","prompt":"[prɒmpt]","project":"[ˈprɒdʒekt]","prohibition":"[ˌprəʊɪˈbɪʃn]","prohibit":"[prəˈhɪbɪt]","programming":"[ˈprəʊɡræmɪŋ]","programmatic":"[ˌprəʊɡrəˈmætɪk]","programmer":"[ˈprəʊɡræmə(r)]","program":"[ˈprəʊɡræm]","profile":"[ˈprəʊfaɪl]","produce":"[prəˈdjuːs]","processed":"[p'rəsest]","processing":"[ˈprəʊsesɪŋ]","process":"[prəˈses;(for n.)ˈprəʊses]","proceed":"[prəˈsiːd]","procedure":"[prəˈsiːdʒə(r)]","problem":"[ˈprɒbləm]","probably":"[ˈprɒbəbli]","privilege":"[ˈprɪvəlɪdʒ]","private":"[ˈpraɪvət]","priority":"[praɪˈɒrəti]","prior to":"","prior":"[ˈpraɪə(r)]","printed":"['prɪntɪd]","print":"[prɪnt]","principal":"[ˈprɪnsəpl]","primitive":"[ˈprɪmətɪv]","prime":"[praɪm]","primarily":"[praɪˈmerəli; ˈpraɪmərəli]","price":"[praɪs]","previously":"[ˈpriːviəsli]","previous":"[ˈpriːviəs]","prevent from..":"","prevent":"[prɪˈvent]","pretty":"[ˈprɪti]","preserve":"[prɪˈzɜːv]","presentation":"[ˌpreznˈteɪʃn]","present":"[ˈpreznt]","presence":"[ˈprezns]","preoccupation":"[priˌɒkjuˈpeɪʃn]","preliminary":"[prɪˈlɪmɪnəri]","prefixed with…":"","prefix":"[ˈpriːfɪks]","preferred":"[prɪ'fɜːd]","preferences":"['pref(ə)r(ə)nsɪz]","preference":"[ˈprefrəns]","preferable to…":"","predefined":"[,pridɪ'faɪnd]","precompiled":"","precompile":"","precompilation":"","precision":"[prɪˈsɪʒn]","precise":"[prɪˈsaɪs]","preceding":"[prɪ'siːdɪŋ]","precedence":"[ˈpresɪdəns]","precede":"[prɪˈsiːd]","practical":"[ˈpræktɪkl]","power":"[ˈpaʊə(r)]","potential":"[pəˈtenʃl]","posting":"[ˈpəʊstɪŋ]","possessive":"[pəˈzesɪv]","positive":"[ˈpɒzətɪv]","positional":"[pəˈzɪʃənəl]","position":"[pəˈzɪʃn]","portion":"[ˈpɔːʃn]","portable":"[ˈpɔːtəbl]","portability":"[ˌpɔːtəˈbɪləti]","port":"[pɔːt]","popularity":"[ˌpɒpjuˈlærəti]","pop":"[pɒp]","pooled":"","poll":"[pəʊl]","polymorphism":"[,pɒlɪ'mɔːfɪz(ə)m]","policy":"[ˈpɒləsi]","pointer":"[ˈpɔɪntə(r)]","point":"[pɔɪnt]","plus":"[plʌs]","plugin":"[plʌgɪn]","platform":"[ˈplætfɔːm]","plant":"[plɑːnt]","plane":"[pleɪn]","plain":"[pleɪn]","placeholder":"[ˈpleɪshoʊldər]","place":"[pleɪs]","pixel":"[ˈpɪksl]","pipe":"[paɪp]","physically":"[ˈfɪzɪkli]","physical":"[ˈfɪzɪkl]","perturb":"[pəˈtɜːb]","perspective":"[pəˈspektɪv]","persistent":"[pəˈsɪstənt]","persist":"[pəˈsɪst]","permute":"[pə'mjuːt]","permutation":"[ˌpɜːmjuˈteɪʃn]","permit":"[pəˈmɪt]","permission":"[pəˈmɪʃn]","permissible":"[pəˈmɪsəbl]","periodical":"[ˌpɪəriˈɒdɪkl]","period":"[ˈpɪəriəd]","performance":"[pəˈfɔːməns]","perform":"[pəˈfɔːm]","perfect":"[ˈpɜːfɪkt]","percentage":"[pəˈsentɪdʒ]","percent":"[pə'sent]","per":"[pə(r); pɜː(r)]","penny":"[ˈpeni]","panel":"[ˈpænl]","pending":"[ˈpendɪŋ]","penalty":"[ˈpenəlti]","peek":"[piːk]","pattern":"[ˈpætn]","pathname":"['pæθ,nem; 'pɑθ,nem]","path":"[pɑːθ]","paste":"[peɪst]","password":"[ˈpɑːswɜːd]","pass in":"","pass around":"","pass along":"","pass":"[pɑːs]","partition":"[pɑːˈtɪʃn]","particular":"[pəˈtɪkjələ(r)]","partially":"[ˈpɑːʃəli]","partial":"[ˈpɑːʃl]","parser":"['pɑːsə]","parse":"[pɑːz]","parentheses":"[pə'renθəsɪz]","parent":"[ˈpeərənt]","parameterized":"[pə'ræmitəraizd]","parametric":"[pærə'metrɪk]","parameter to…":"","parameter":"[pəˈræmɪtə(r)]","parallelism":"[ˈpærəlelɪzəm]","paradigm":"[ˈpærədaɪm]","page encoding":"","page context":"","page":"[peɪdʒ]","padding":"[ˈpædɪŋ]","pad with..":"","pad":"[pæd]","package explorer":"","package":"[ˈpækɪdʒ]","quality":"[ˈkwɒləti]","quietly":"[ˈkwaɪətli]","quiet":"[ˈkwaɪət]","quotation":"[kwəʊˈteɪʃn]","question":"[ˈkwestʃən]","quick":"[kwɪk]","quit":"[kwɪt]","quotient":"[ˈkwəʊʃnt]","quote":"[kwəʊt]","quickly":"[ˈkwɪkli]","queue":"[kjuː]","query":"[ˈkwɪəri]","quantifier":"[ˈkwɒntɪfaɪə(r)]","qualify…with…":"","qualify":"[ˈkwɒlɪfaɪ]","qualifier":"[ˈkwɒlɪfaɪə(r)]","qualified":"[ˈkwɒlɪfaɪd]","quadratic":"[kwɒˈdrætɪk]","reduction":"[rɪˈdʌkʃn]","representative":"[ˌreprɪˈzentətɪv]","restricted":"[rɪˈstrɪktɪd]","rectangular":"[rekˈtæŋɡjələ(r)]","rearrange":"[ˌriːəˈreɪndʒ]","reenter":"[,riː'entə]","repetitive":"[rɪˈpetətɪv]","repeating":"[rɪ'piːtɪŋ]","rewrite":"[ˈriːraɪt]","reorganization":"[riˌɔːɡənaɪˈzeɪʃn]","reload":"[ˌriːˈləʊd]","reappears":"[ˌriːəˈpɪə(r)]","recoverable":"[rɪˈkʌvərəbl]","readable":"[ˈriːdəbl]","regard":"[rɪˈɡɑːd]","reactivate":"[riˈæktɪveɪt]","roll":"[rəʊl]","reinstate":"[ˌriːɪnˈsteɪt]","real":"[ˈriːəl; rɪəl]","revolutionize":"[ˌrevəˈluːʃənaɪz]","restricting":"[rɪ'strɪkt]","really":"[ˈriːəli; ˈrɪəli]","rebuild":"[ˌriːˈbɪld]","replicate":"[ˈreplɪkeɪt]","registration":"[ˌredʒɪˈstreɪʃn]","restructure":"[ˌriːˈstrʌktʃə(r)]","review":"[rɪˈvjuː]","regular":"[ˈreɡjələ(r)]","rated":"['reɪtɪd]","recursive":"[rɪˈkɜːsɪv]","ring":"[rɪŋ]","reread":"[riː'riːd]","replaceable":"[rɪˈpleɪsəbl]","recently":"[ˈriːsntli]","received":"[rɪˈsiːvd]","route":"[ruːt]","reserved":"[rɪˈzɜːvd]","rest":"[rest]","remember":"[rɪˈmembə(r)]","rent":"[rent]","respect":"[rɪˈspekt]","reason":"[ˈriːzn]","rating":"[ˈreɪtɪŋ]","reformat":"[ˌriːˈfɔːrmæt]","reading":"[ˈriːdɪŋ]","reach":"[riːtʃ]","restart":"[ˈriːstɑːt]","red":"[red]","reindex":"","ram":"[ræm]","rectangle":"[ˈrektæŋɡl]","redraw":"[ˌriːˈdrɔː]","ready":"[ˈredi]","routine":"[ruːˈtiːn]","readily":"[ˈredɪli]","resident":"[ˈrezɪdənt]","retry":"[ˌriːˈtraɪ]","rather":"[ˈrɑːðə(r)]","repaint":"[riː'peɪnt]","refer":"[rɪˈfɜː(r)]","recall":"[rɪˈkɔːl]","recover":"[rɪˈkʌvə(r)]","running":"[ˈrʌnɪŋ]","read":"[riːd]","reflow":"[ˈriːfloʊ]","returned":"[rɪ'tɜːnd]","related":"[rɪˈleɪtɪd]","record":"[ˈrekɔːd]","runtime":"[ˈrʌntaɪm]","runnable":"['rʌnəbl]","run inside…":"","run":"[rʌn]","rule":"[ruːl]","row":"[rəʊ]","round":"[raʊnd]","roughly":"[ˈrʌfli]","root":"[ruːt]","room":"[ruːm; rʊm]","roll back":"","robust":"[rəʊˈbʌst]","risk":"[rɪsk]","rise to…":"","rightmost":"[ˈraɪtmoʊst]","right":"[raɪt]","reverse":"[rɪˈvɜːs]","re-use":"['ri:'ju:z]","return":"[rɪˈtɜːn]","retrofit":"[ˈretrəʊfɪt]","retrieve":"[rɪˈtriːv]","retention":"[rɪˈtenʃn]","retain":"[rɪˈteɪn]","resume":"[rɪˈzjuːm]","resultset":"","resulting":"[rɪ'zʌltɪŋ]","resultant":"[rɪˈzʌltənt]","result from":"","result":"[rɪˈzʌlt]","restriction":"[rɪˈstrɪkʃn]","restrict":"[rɪˈstrɪkt]","restore":"[rɪˈstɔː(r)]","responsible":"[rɪˈspɒnsəbl]","responsibility":"[rɪˌspɒnsəˈbɪləti]","response":"[rɪˈspɒns]","responder":"[rɪ'spɒndə]","respond":"[rɪˈspɒnd]","respectively":"[rɪˈspektɪvli]","resolve…against...":"","resolve":"[rɪˈzɒlv]","resource":"[rɪˈsɔːs; rɪˈzɔːs]","resolution":"[ˌrezəˈluːʃn]","resizable":"","reside":"[rɪˈzaɪd]","reset":"[ˌriːˈset]","reserve":"[rɪˈzɜːv]","required":"[rɪ'kwaɪəd]","require":"[rɪˈkwaɪə(r)]","requested":"[rɪ'kwɛst]","request":"[rɪˈkwest]","reptile":"[ˈreptaɪl]","represented":"[reprɪ'zentɪd]","representation":"[ˌreprɪzenˈteɪʃn]","represent":"[ˌreprɪˈzent]","report":"[rɪˈpɔːt]","repository":"[rɪˈpɒzətri]","replace with…":"","replacement":"[rɪˈpleɪsmənt]","replace":"[rɪˈpleɪs]","repeatedly":"[rɪˈpiːtɪdli]","repeated":"[rɪˈpiːtɪd]","repeat":"[rɪˈpiːt]","reorder":"[ˌriːˈɔːdə(r)]","render":"[ˈrendə(r)]","rename":"[ˌriːˈneɪm]","remove":"[rɪˈmuːv]","removal":"[rɪˈmuːvl]","removable":"[rɪˈmuːvəbl]","remote":"[rɪˈməʊt]","remark":"[rɪˈmɑːk]","remainder":"[rɪˈmeɪndə(r)]","remain":"[rɪˈmeɪn]","rely on":"","reluctant":"[rɪˈlʌktənt]","relinquish":"[rɪˈlɪŋkwɪʃ]","reliably":"[rɪˈlaɪəbli]","reliable":"[rɪˈlaɪəbl]","relevant":"[ˈreləvənt]","release":"[rɪˈliːs]","relative to…":"","relative against…":"","relative":"[ˈrelətɪv]","relational":"[rɪˈleɪʃənl]","relation":"[rɪˈleɪʃn]","rehash":"[ˈriːhæʃ]","registered":"['redʒɪstəd]","register":"[ˈredʒɪstə(r)]","region":"[ˈriːdʒən]","regardless of":"","regardless":"[rɪˈɡɑːdləs]","regarding":"[rɪˈɡɑːdɪŋ]","refresh":"[rɪˈfreʃ]","reflecting":"[rɪ'flektɪŋ]","reflected":"[rɪ'flektɪd]","reflect":"[rɪˈflekt]","refill":"[(for v.)riːˈfɪl; (for n.)ˈriːfɪl]","referer":"","referenced":"","reference":"[ˈrefrəns]","refer to…":"","refactor":"[ri'fæktə]","redundant":"[rɪˈdʌndənt]","reduce":"[rɪˈdjuːs]","redirect":"[ˌriːdəˈrekt; ˌriːdaɪˈrekt]","redefine":"[ˌriːdɪˈfaɪn]","recursively":"[ri'kəsivli]","recursion":"[rɪˈkɜːʃn]","recurse":"","recommendation":"[ˌrekəmenˈdeɪʃn]","recommend":"[ˌrekəˈmend]","recognize":"[ˈrekəɡnaɪz]","recent":"[ˈriːsnt]","receive":"[rɪˈsiːv]","reasonably":"[ˈriːznəbli]","reallocation":"[ˌriːˌæləˈkeɪʃn]","read in":"","read of…":"","read back in":"","re-execute":"","raw":"[rɔː]","ratio":"[ˈreɪʃiəʊ]","rate":"[reɪt]","rare":"[reə(r)]","range":"[reɪndʒ]","randomness":"[ˈrændəmnəs]","random":"[ˈrændəm]","raise":"[reɪz]","radix":"['rædɪks; 'reɪ-]","radius":"[ˈreɪdiəs]","sale":"[seɪl]","sound":"[saʊnd]","succession":"[səkˈseʃn]","situation":"[ˌsɪtʃuˈeɪʃn]","social":"[ˈsəʊʃl]","stated":"['steɪtɪd]","sufficient":"[səˈfɪʃnt]","seamless":"[ˈsiːmləs]","suspension":"[səˈspenʃn]","supposed":"[səˈpəʊzd]","shut":"[ʃʌt]","superimpose":"[ˌsuːpərɪmˈpəʊz; ˌsjuːpərɪmˈpəʊz]","subgroup":"[ˈsʌbɡruːp]","scattered":"[ˈskætəd]","significant":"[sɪɡˈnɪfɪkənt]","specifically":"[spəˈsɪfɪkli]","strike":"[straɪk]","shield":"[ʃiːld]","smooth":"[smuːð]","stamp":"[stæmp]","slowly":"[ˈsləʊli]","spread":"[spred]","squeeze":"[skwiːz]","substantial":"[səbˈstænʃl]","suggestion":"[səˈdʒestʃən]","seldom":"[ˈseldəm]","safely":"[ˈseɪfli]","stopping":"['stɒpɪŋ]","ship":"[ʃɪp]","somewhat":"[ˈsʌmwɒt]","sensitivity":"[ˌsensəˈtɪvəti]","snapshot":"[ˈsnæpʃɒt]","showing":"[ˈʃəʊɪŋ]","subroutine":"[ˈsʌbruːtiːn]","suppressed":"[sə'prest]","specialize":"[ˈspeʃəlaɪz]","substantially":"[səbˈstænʃəli]","strong":"[strɒŋ]","salary":"[ˈsæləri]","sit":"[sɪt]","separately":"[ˈseprətli]","spell":"[spel]","stationary":"[ˈsteɪʃənri]","stay":"[steɪ]","sounding":"[ˈsaʊndɪŋ]","seven":"[ˈsevn]","soft":"[sɒft]","surrounding":"[səˈraʊndɪŋ]","stuff":"[stʌf]","suggest":"[səˈdʒest]","skill":"[skɪl]","safe":"[seɪf]","scatter":"[ˈskætə(r)]","slide":"[slaɪd]","star":"[stɑː(r)]","skeleton":"[ˈskelɪtn]","stand":"[stænd]","sample":"[ˈsɑːmpl]","sentence":"[ˈsentəns]","signal":"[ˈsɪɡnəl]","setup":"['setʌp]","six":"[sɪks]","series":"[ˈsɪəriːz]","splitting":"[ˈsplɪtɪŋ]","successful":"[səkˈsesfl]","sun":"[sʌn]","secondary":"[ˈsekəndri]","subscript":"[ˈsʌbskrɪpt]","seek":"[siːk]","sector":"[ˈsektə(r)]","subtotal":"[ˈsʌbtəʊtl]","speed":"[spiːd]","small":"[smɔːl]","separated":"[ˈsepəreɪtɪd]","searching":"[ˈsɜːtʃɪŋ]","still":"[stɪl]","side":"[saɪd]","stop":"[stɒp]","slow":"[sləʊ]","say":"[seɪ]","saving":"[ˈseɪvɪŋ]","speech":"[spiːtʃ]","spill":"[spɪl]","switching":"['swɪtʃɪŋ]","since":"[sɪns]","shortcut":"[ˈʃɔːtkʌt]","sub-directory":"","starting":"['stɑrtɪŋ]","second":"['sek(ə)nd]","section":"[ˈsekʃn]","sure":"[ʃʊə(r); ʃɔː(r)]","so":"[səʊ]","such":"[sʌtʃ]","should":"[ʃəd; ʃʊd]","scroll":"[skrəʊl]","same":"[seɪm]","selection":"[sɪˈlekʃn]","start":"[stɑːt]","shell":"[ʃel]","system-level":"","system":"[ˈsɪstəm]","syntax":"[ˈsɪntæks]","syntactically":"[sɪnˈtæktɪkli]","synchronized":"['sɪŋkrənaɪzd]","synchronization":"[ˌsɪŋkrənaɪˈzeɪʃn]","synchronize":"[ˈsɪŋkrənaɪz]","symmetric":"[sɪ'metrɪk]","symbol":"[ˈsɪmbl]","switch workspace":"","switch":"[swɪtʃ]","swap":"[swɒp]","suspend":"[səˈspend]","surrogate pair":"","surrogate":"[ˈsʌrəɡət]","surprisingly":"[səˈpraɪzɪŋli]","support":"[səˈpɔːt]","supply…with…":"","supplied":"[sə'plaɪd]","supply":"[səˈplaɪ]","supplementary":"[ˌsʌplɪˈmentri]","suppress":"[səˈpres]","suppose":"[səˈpəʊz]","superimposed":"['sjuːpəɪm'pəʊzd]","superclass":"['suːpəklɑːs; 'sjuː-]","super":"[ˈsuːpə(r); ˈsjuːpə(r)]","summary":"[ˈsʌməri]","sum":"[sʌm]","suitable for…":"","suitable":"[ˈsuːtəbl; ˈsjuːtəbl]","suffix":"[ˈsʌfɪks]","sufficiently":"[səˈfɪʃntli]","successive":"[səkˈsesɪv]","successfully":"[səkˈsesfəli]","succeeding":"[sək'siːdɪŋ]","succeed":"[səkˈsiːd]","substraction":"","subtract":"[səbˈtrækt]","subtag":"","substitution":"[ˌsʌbstɪˈtjuːʃn]","substitute":"[ˈsʌbstɪtjuːt]","subset":"[ˈsʌbset]","subsequently":"[ˈsʌbsɪkwəntli]","subsequent":"[ˈsʌbsɪkwənt]","subsequence":"['sʌbsɪkw(ə)ns]","subscription":"[səbˈskrɪpʃn]","subscriber":"[səbˈskraɪbə(r)]","submit":"[səbˈmɪt]","subject":"[ˈsʌbdʒɪkt; ˈsʌbdʒekt]","subclass":"['sʌbklɑːs]","style sheet":"","style":"[staɪl]","stub":"[stʌb]","structured":"['strʌktʃəd]","structure":"[ˈstrʌktʃə(r)]","structurally":"[ˈstrʌktʃərəli]","structural":"[ˈstrʌktʃərəl]","strip":"[strɪp]","string":"[strɪŋ]","strictly":"[ˈstrɪktli]","strict":"[strɪkt]","stream":"[striːm]","strategy":"[ˈstrætədʒi]","strange":"[streɪndʒ]","store":"[stɔː(r)]","storage":"[ˈstɔːrɪdʒ]","stipulation":"[ˌstɪpjuˈleɪʃn]","step into":"","step":"[step]","status":"[ˈsteɪtəs]","static":"[ˈstætɪk]","statement":"[ˈsteɪtmənt]","state":"[steɪt]","startup":"[stɑ:tʌp]","starting with…":"","starting at the beginning":"","start at…":"","stark":"[stɑːk]","standpoint":"[ˈstændpɔɪnt]","standard":"[ˈstændəd]","stand alone":"","staging":"[ˈsteɪdʒɪŋ]","stack":"[stæk]","stable":"[ˈsteɪbl]","square":"[skweə(r)]","spurious":"[ˈspjʊəriəs]","spot":"[spɒt]","split":"[splɪt]","spend":"[spend]","specified":"[ˈspesɪfaɪd]","specify":"[ˈspesɪfaɪ]","specifier":"['spesifaiə]","specification":"[ˌspesɪfɪˈkeɪʃn]","specific":"[spəˈsɪfɪk]","specialized":"[ˈspeʃəlaɪzd]","special":"[ˈspeʃl]","sparingly":"[ˈspeərɪŋli]","spare":"[speə(r)]","span":"[spæn]","space":"[speɪs]","source":"[sɔːs]","sorting":"['sɔːtɪŋ]","sorted":"[ˈsɔːtɪd]","sort…into…":"","sort by…":"","sort":"[sɔːt]","sophisticated":"[səˈfɪstɪkeɪtɪd]","solution":"[səˈluːʃn]","solely":"[ˈsəʊlli]","software":"[ˈsɒftweə(r)]","socket":"[ˈsɒkɪt]","so as to…":"","slight":"[slaɪt]","sleep":"[sliːp]","slash":"[slæʃ]","skip":"[skɪp]","size":"[saɪz]","sink":"[sɪŋk]","single-valued":"","single":"[ˈsɪŋɡl]","simply":"[ˈsɪmpli]","simple":"[ˈsɪmpl]","similarly":"[ˈsɪmələli]","similar":"[ˈsɪmələ(r)]","significantly":"[sɪɡˈnɪfɪkəntli]","signum":"['siɡnəm]","signature":"[ˈsɪɡnətʃə(r)]","sign":"[saɪn]","side effects":"","sibling":"[ˈsɪblɪŋ]","shutdown":"[ˈʃʌtdaʊn]","shuffle":"[ˈʃʌfl]","shrink":"[ʃrɪŋk]","show":"[ʃəʊ]","shorten":"[ˈʃɔːtn]","short":"[ʃɔːt]","shorthand":"[ˈʃɔːthænd]","shim":"[ʃɪm]","shift":"[ʃɪft]","sheet":"[ʃiːt]","shared":"[ʃeəd]","share":"[ʃeə(r)]","shape":"[ʃeɪp]","several":"[ˈsevrəl]","setting":"[ˈsetɪŋ]","setter":"[ˈsetə(r)]","set":"[set]","session":"[ˈseʃn]","service":"[ˈsɜːvɪs]","server as…":"","server":"[ˈsɜːvə(r)]","serve to…":"","serious":"[ˈsɪəriəs]","serialize":"[ˈsɪəriəlaɪz]","serialization":"[ˌsɪəriəlaɪˈzeɪʃn]","serializable":"","serializability":"['siəriə,laizəbiliti]","serial":"[ˈsɪəriəl]","sequentially":"[sɪˈkwenʃəli]","sequential":"[sɪˈkwenʃl]","sequence":"[ˈsiːkwəns]","separator":"[ˈsepəreɪtə(r)]","separate":"[ˈseprət]","sensitive":"[ˈsensətɪv]","sensible":"[ˈsensəbl]","send":"[send]","semicolon":"[ˌsemiˈkəʊlən; ˌsemiˈkəʊlɒn]","semantics":"[sɪˈmæntɪks]","selected":"[sɪ'lektɪd]","select":"[sɪˈlekt]","segment":"[ˈseɡmənt]","see":"[siː]","security":"[sɪˈkjʊərəti]","search for":"","search":"[sɜːtʃ]","scrollable":"['skrəuləbl]","script":"[skrɪpt]","screen":"[skriːn]","score":"[skɔː(r)]","scoped variable":"","scope":"[skəʊp]","scheme":"[skiːm]","scanner":"[ˈskænə(r)]","scan":"[skæn]","save…as…":"","save":"[seɪv]","satisfy":"[ˈsætɪsfaɪ]","satellite":"[ˈsætəlaɪt]","safety":"[ˈseɪfti]","terminology":"[ˌtɜːmɪˈnɒlədʒi]","tone":"[təʊn]","typewriter":"[ˈtaɪpraɪtə(r)]","telephone":"[ˈtelɪfəʊn]","turnkey":"[ˈtɜːnkiː]","terminating":"['tɜːmɪneɪtɪŋ]","teach":"[tiːtʃ]","talent":"[ˈtælənt]","tension":"[ˈtenʃn]","technical":"[ˈteknɪkl]","think":"[θɪŋk]","tutorial":"[tjuːˈtɔːriəl]","touch":"[tʌtʃ]","traditional":"[trəˈdɪʃənl]","twentieth":"[ˈtwentiəθ]","thousand":"[ˈθaʊznd]","tornado":"[tɔːˈneɪdəʊ]","tape":"[teɪp]","translation":"[trænzˈleɪʃn; trænsˈleɪʃn]","turning":"[ˈtɜːnɪŋ]","trap":"[træp]","trying":"[ˈtraɪɪŋ]","trouble":"[ˈtrʌbl]","tool":"[tuːl]","throughout":"[θruːˈaʊt]","toward":"[tə'wɔːd; twɔːd; tɔːd]","track":"[træk]","technology":"[tekˈnɒlədʒi]","today":"[təˈdeɪ]","together":"[təˈɡeðə(r)]","tiny":"[ˈtaɪni]","twice":"[twaɪs]","transfer":"[trænsˈfɜː(r)]","tick":"[tɪk]","third":"[θɜːd]","transportable":"[trænˈspɔːtəbl]","talk":"[tɔːk]","temporarily":"[ˈtemprərəli]","term":"[tɜːm]","times":"[taɪmz]","tell":"[tel]","three":"[θriː]","try":"[traɪ]","turn":"[tɜːn]","two":"[tuː]","time":"[taɪm]","topic":"[ˈtɒpɪk]","then":"[ðen]","tyre":"[ˈtaɪə(r)]","typically":"[ˈtɪpɪkli]","typical":"[ˈtɪpɪkl]","type":"[taɪp]","tying up":"","tweaks":"","turn off":"","tuned":"[tjuːnd]","truncate":"[trʌŋˈkeɪt]","truly":"[ˈtruːli]","true":"[truː]","trim":"[trɪm]","trigger":"[ˈtrɪɡə(r)]","triangle":"[ˈtraɪæŋɡl]","tree":"[triː]","treat":"[triːt]","traverse":"['trævɜːs; trə'vɜːs]","transmit":"[trænzˈmɪt; trænsˈmɪt]","translate":"[trænzˈleɪt; trænsˈleɪt]","transitive":"[ˈtrænzətɪv; ˈtrænsətɪv]","transient":"[ˈtrænziənt]","transform":"[trænsˈfɔːm]","transaction":"[trænˈzækʃn]","trailing":"['treɪlɪŋ]","tradeoff":"['tred,ɔf]","tracking":"['trækɪŋ]","trace":"[treɪs]","totally":"[ˈtəʊtəli]","top":"[tɒp]","total":"[ˈtəʊtl]","tokenizing":"","tokenizer":"","token":"[ˈtəʊkən]","toggle":"[ˈtɒɡl]","title":"[ˈtaɪtl]","timestamp":"['taimstæmp]","timeout":"[ˈtaɪmaʊt]","time-consuming":"[ˈtaɪm kənsjuːmɪŋ]","thus":"[ðʌs]","throw":"[θrəʊ]","through":"[θruː]","thrice":"[θraɪs]","thread":"[θred]","though":"[ðəʊ]","third-party":"[ˌθɜːrd ˈpɑːrti]","thin":"[θɪn]","thereof":"[ˌðeərˈɒv]","therein":"[ˌðeərˈɪn]","therefore":"[ˈðeəfɔː(r)]","thereafter":"[ˌðeərˈɑːftə(r)]","theme":"[θiːm]","the rest of…":"","that is…":"","textually":"['tɛkstʃʊəli]","textual":"[ˈtekstʃuəl]","text":"[tekst]","test":"[test]","terminator":"['tɜːmɪneɪtə]","termination":"[ˌtɜːmɪˈneɪʃn]","terminate":"[ˈtɜːmɪneɪt]","terminal":"[ˈtɜːmɪnl]","temporary":"[ˈtemprəri]","template":"[ˈtempleɪt]","temp":"[temp]","technique":"[tekˈniːk]","team":"[tiːm]","take over":"","task":"[tɑːsk]","target":"[ˈtɑːɡɪt]","tandem":"[ˈtændəm]","take the place of":"","take out of…":"","take into account…":"","take care to…":"","take advantage of":"","take":"[teɪk]","tailor":"[ˈteɪlə(r)]","tail":"[teɪl]","tag library":"","tag":"[tæɡ]","table":"[ˈteɪbl]","tab":"[tæb]","unpack":"[ˌʌnˈpæk]","useless":"[ˈjuːsləs]","unformatted":"[ʌn'fɔr,mætɪd]","university":"[ˌjuːnɪˈvɜːsəti]","unsafe":"[ʌnˈseɪf]","unmarked":"[ˌʌnˈmɑːkt]","unused":"[,ʌn'juːzd]","unwanted":"[ˌʌnˈwɒntɪd]","unchanged":"[ʌnˈtʃeɪndʒd]","unnecessary":"[ʌnˈnesəsəri]","unknown":"[ˌʌnˈnəʊn]","unshift":"[ʌn'ʃɪft]","undone":"[ʌnˈdʌn]","unfortunately":"[ʌnˈfɔːtʃənətli]","understanding":"[ˌʌndəˈstændɪŋ]","unavailable":"[ˌʌnəˈveɪləbl]","undesirable":"[ˌʌndɪˈzaɪərəbl]","unrecognized":"[ʌnˈrekəɡnaɪzd]","upon":"[əˈpɒn]","understand":"[ˌʌndəˈstænd]","upgrade":"[ˈʌpɡreɪd]","unsuccessful":"[ˌʌnsəkˈsesfl]","unlock":"[ˌʌnˈlɒk]","usually":"[ˈjuːʒuəli; ˈjuːʒəli]","underscore":"[ʌndə'skɔː]","unable":"[ʌnˈeɪbl]","undo":"[ʌnˈduː]","under":"[ˈʌndə(r)]","useful":"[ˈjuːsfl]","unless":"[ənˈles]","until":"[ənˈtɪl]","user":"[ˈjuːzə(r)]","up":"[ʌp]","use":"[juːz]","utility":"[juːˈtɪləti]","usual":"[ˈjuːʒuəl; ˈjuːʒəl]","usage":"[ˈjuːsɪdʒ; ˈjuːzɪdʒ]","uppercase":"['ʌpə'keɪs]","upper":"[ˈʌpə(r)]","upload":"[ˌʌpˈləʊd]","underlying":"[ˌʌndəˈlaɪɪŋ]","updater":"","updated":"[ʌp'deɪtɪd]","update":"[ˌʌpˈdeɪt]","updatable":"['ʌp,deitəbl]","upcasting":"","unwrapping":"[ʌn'ræp]","unwrap":"[ʌnˈræp]","untouched":"[ʌnˈtʌtʃt]","until…":"[ənˈtɪl]","unspecified":"[ʌnˈspesɪfaɪd]","unsigned":"[ʌn'saɪnd]","unselectable":"","unmounting":"","unmodifiable":"['ʌn'mɔdifaiəbl]","unlimited":"[ʌnˈlɪmɪtɪd]","unlike":"[ˌʌnˈlaɪk]","unless otherwise mentioned":"","universally":"[ˌjuːnɪˈvɜːsəli]","universal":"[ˌjuːnɪˈvɜːsl]","unit":"[ˈjuːnɪt]","uniquely":"[juˈniːkli]","unique":"[juˈniːk]","union":"[ˈjuːniən]","uninitialized":"","uniformity":"[ˌjuːnɪˈfɔːməti]","uniformly":"[ˈjuːnɪfɔːmli]","uniform":"[ˈjuːnɪfɔːm]","unfortunatly":"","unexpected":"[ˌʌnɪkˈspektɪd]","unencoded":"","undetermined":"[ʌndɪ'tɜːmɪnd]","underneath":"[ˌʌndəˈniːθ]","underline":"[ˌʌndəˈlaɪn]","undefined":"[ˌʌndɪˈfaɪnd]","unbind":"[ʌn'baɪnd]","unbiased":"[ʌnˈbaɪəst]","unaffected":"[ˌʌnəˈfektɪd]","vital":"[ˈvaɪtl]","varying":"['vɛəriŋ]","visual":"[ˈvɪʒuəl]","very":"[ˈveri]","vowel":"[ˈvaʊəl]","vice":"[vaɪs]","volume":"[ˈvɒljuːm]","valuable":"[ˈvæljuəbl]","vertically":"[ˈvɜːtɪkli]","variety":"[vəˈraɪəti]","video":"[ˈvɪdiəʊ]","volatile":"[ˈvɒlətaɪl]","volant":"['vəʊlənt]","void":"[vɔɪd]","visit":"[ˈvɪzɪt]","visible":"[ˈvɪzəbl]","visibility":"[ˌvɪzəˈbɪləti]","virtually":"[ˈvɜːtʃuəli]","virtual":"[ˈvɜːtʃuəl]","violate":"[ˈvaɪəleɪt]","viewport":"[ˈvjuːpɔːrt]","view":"[vjuː]","vice-versa":"[ˌvaɪs ˈvɜːrsə,ˌvaɪsi ˈvɜːrsə]","via":"[ˈvaɪə; ˈviːə]","vessel":"[ˈvesl]","vertical":"[ˈvɜːtɪkl]","version":"[ˈvɜːʃn]","verify":"[ˈverɪfaɪ]","verification":"[ˌverɪfɪˈkeɪʃn]","verbose":"[vɜːˈbəʊs]","vendor":"[ˈvendə(r)]","vehicle":"[ˈviːəkl]","vector":"[ˈvektə(r)]","vary":"[ˈveəri]","various":"[ˈveəriəs]","variant":"[ˈveəriənt]","variable":"[ˈveəriəbl]","value":"[ˈvæljuː]","validator":"['vali,deitə]","validation":"[ˌvælɪˈdeɪʃn]","validate":"[ˈvælɪdeɪt]","valid":"[ˈvælɪd]","wise":"[waɪz]","waiting":"[ˈweɪtɪŋ]","ware":"[weə(r)]","world":"[wɜːld]","widely":"[ˈwaɪdli]","worker":"[ˈwɜːkə(r)]","watch":"[wɒtʃ]","worry":"[ˈwʌri]","wide":"[waɪd]","week":"[wiːk]","whole":"[həʊl]","warranty":"[ˈwɒrənti]","whatever":"[wɒtˈevə(r)]","warn":"[wɔːn]","windowing":"['wɪndo]","white":"[waɪt]","wrong":"[rɒŋ]","wrap":"[ræp]","welcome":"[ˈwelkəm]","wordperfect":"","whenever":"[wenˈevə(r)]","well":"[wel]","wait":"[weɪt]","wish":"[wɪʃ]","whose":"[huːz]","why":"[waɪ]","working":"[ˈwɜːkɪŋ]","write":"[raɪt]","whether":"[ˈweðə(r)]","way":"[weɪ]","word":"[wɜːd]","window":"[ˈwɪndəʊ]","want":"[wɒnt]","which":"[wɪtʃ]","with":"[wɪð; wɪθ]","write out":"","wrapper":"[ˈræpə(r)]","wrap…with…":"","wrap…around…":"","work":"[wɜːk]","without the need":"","withouot have to…":"","without":"[wɪˈðaʊt]","within":"[wɪˈðɪn]","with respect to…":"","with no regard to…":"","wildcard":"['waɪldkɑrd]","width":"[wɪdθ; wɪtθ]","widening":"['waɪdəʊɪŋ]","whitespace":"","while":"[waɪl]","whichever":"[wɪtʃˈevə(r)]","wherever":"[weərˈevə(r)]","whereby":"[weəˈbaɪ]","whereas":"[ˌweərˈæz]","weight":"[weɪt]","wasted":"[ˈweɪstɪd]","warning":"[ˈwɔːnɪŋ]","wake up":"","yet":"[jet]","yellow":"[ˈjeləʊ]","year":"[jɪə(r); jɜː(r)]","yield to":"","yield":"[jiːld]","zap":"[zæp]","zero":"[ˈzɪərəʊ]","zoom":"[zuːm]"}